[
  {
    "line": 13,
    "token": 11748,
    "index": 0,
    "confidence": 0.5,
    "severity": null
  },
  {
    "line": 13,
    "token": 299,
    "index": 1,
    "confidence": 0.5,
    "severity": null
  },
  {
    "line": 13,
    "token": 32152,
    "index": 2,
    "confidence": 0.5,
    "severity": null
  },
  {
    "line": 13,
    "token": 355,
    "index": 3,
    "confidence": 0.5,
    "severity": null
  },
  {
    "line": 13,
    "token": 45941,
    "index": 4,
    "confidence": 0.5,
    "severity": null
  },
  {
    "line": 18,
    "token": 6738,
    "index": 0,
    "confidence": 0.0,
    "severity": null
  },
  {
    "line": 18,
    "token": 10662,
    "index": 1,
    "confidence": 0.0,
    "severity": null
  },
  {
    "line": 18,
    "token": 8019,
    "index": 2,
    "confidence": 0.0,
    "severity": null
  },
  {
    "line": 18,
    "token": 13,
    "index": 3,
    "confidence": 0.0,
    "severity": null
  },
  {
    "line": 18,
    "token": 1891,
    "index": 4,
    "confidence": 0.0,
    "severity": null
  },
  {
    "line": 18,
    "token": 9288,
    "index": 5,
    "confidence": 0.5,
    "severity": null
  },
  {
    "line": 18,
    "token": 1330,
    "index": 6,
    "confidence": 0.5,
    "severity": null
  },
  {
    "line": 18,
    "token": 24413,
    "index": 7,
    "confidence": 0.5,
    "severity": null
  },
  {
    "line": 18,
    "token": 2149,
    "index": 8,
    "confidence": 0.5,
    "severity": null
  },
  {
    "line": 18,
    "token": 25633,
    "index": 9,
    "confidence": 0.5,
    "severity": null
  },
  {
    "line": 18,
    "token": 62,
    "index": 10,
    "confidence": 0.5,
    "severity": null
  },
  {
    "line": 18,
    "token": 47123,
    "index": 11,
    "confidence": 0.5,
    "severity": null
  },
  {
    "line": 18,
    "token": 41132,
    "index": 12,
    "confidence": 0.5,
    "severity": null
  },
  {
    "line": 18,
    "token": 11,
    "index": 13,
    "confidence": 0.5,
    "severity": null
  },
  {
    "line": 18,
    "token": 2824,
    "index": 14,
    "confidence": 0.5,
    "severity": null
  },
  {
    "line": 18,
    "token": 62,
    "index": 15,
    "confidence": 0.5,
    "severity": null
  },
  {
    "line": 18,
    "token": 7890,
    "index": 16,
    "confidence": 0.5,
    "severity": null
  },
  {
    "line": 18,
    "token": 62,
    "index": 17,
    "confidence": 0.5,
    "severity": null
  },
  {
    "line": 18,
    "token": 26268,
    "index": 18,
    "confidence": 0.5,
    "severity": null
  },
  {
    "line": 18,
    "token": 11,
    "index": 19,
    "confidence": 0.5,
    "severity": null
  },
  {
    "line": 18,
    "token": 651,
    "index": 20,
    "confidence": 0.5,
    "severity": null
  },
  {
    "line": 18,
    "token": 62,
    "index": 21,
    "confidence": 0.5,
    "severity": null
  },
  {
    "line": 18,
    "token": 2536,
    "index": 22,
    "confidence": 0.5,
    "severity": null
  },
  {
    "line": 18,
    "token": 4338,
    "index": 23,
    "confidence": 0.5,
    "severity": null
  },
  {
    "line": 18,
    "token": 62,
    "index": 24,
    "confidence": 0.5,
    "severity": null
  },
  {
    "line": 18,
    "token": 18558,
    "index": 25,
    "confidence": 0.5,
    "severity": null
  },
  {
    "line": 18,
    "token": 38409,
    "index": 26,
    "confidence": 0.5,
    "severity": null
  },
  {
    "line": 20,
    "token": 6738,
    "index": 0,
    "confidence": 0.0,
    "severity": null
  },
  {
    "line": 20,
    "token": 10662,
    "index": 1,
    "confidence": 0.0,
    "severity": null
  },
  {
    "line": 20,
    "token": 8019,
    "index": 2,
    "confidence": 0.0,
    "severity": null
  },
  {
    "line": 20,
    "token": 13,
    "index": 3,
    "confidence": 0.0,
    "severity": null
  },
  {
    "line": 20,
    "token": 1891,
    "index": 4,
    "confidence": 0.0,
    "severity": null
  },
  {
    "line": 20,
    "token": 9288,
    "index": 5,
    "confidence": 0.0,
    "severity": null
  },
  {
    "line": 20,
    "token": 13,
    "index": 6,
    "confidence": 0.0,
    "severity": null
  },
  {
    "line": 20,
    "token": 18558,
    "index": 7,
    "confidence": 0.0,
    "severity": null
  },
  {
    "line": 20,
    "token": 38409,
    "index": 8,
    "confidence": 0.0,
    "severity": null
  },
  {
    "line": 20,
    "token": 1330,
    "index": 9,
    "confidence": 0.0,
    "severity": null
  },
  {
    "line": 20,
    "token": 13942,
    "index": 10,
    "confidence": 0.0,
    "severity": null
  },
  {
    "line": 20,
    "token": 23002,
    "index": 11,
    "confidence": 0.0,
    "severity": null
  },
  {
    "line": 20,
    "token": 38409,
    "index": 12,
    "confidence": 0.0,
    "severity": null
  },
  {
    "line": 22,
    "token": 6738,
    "index": 0,
    "confidence": 0.0,
    "severity": null
  },
  {
    "line": 22,
    "token": 10662,
    "index": 1,
    "confidence": 0.0,
    "severity": null
  },
  {
    "line": 22,
    "token": 8019,
    "index": 2,
    "confidence": 0.0,
    "severity": null
  },
  {
    "line": 22,
    "token": 13,
    "index": 3,
    "confidence": 0.0,
    "severity": null
  },
  {
    "line": 22,
    "token": 45895,
    "index": 4,
    "confidence": 0.0,
    "severity": null
  },
  {
    "line": 22,
    "token": 13,
    "index": 5,
    "confidence": 0.0,
    "severity": null
  },
  {
    "line": 22,
    "token": 3642,
    "index": 6,
    "confidence": 0.0,
    "severity": null
  },
  {
    "line": 22,
    "token": 822,
    "index": 7,
    "confidence": 0.0,
    "severity": null
  },
  {
    "line": 22,
    "token": 13,
    "index": 8,
    "confidence": 0.0,
    "severity": null
  },
  {
    "line": 22,
    "token": 2616,
    "index": 9,
    "confidence": 0.0,
    "severity": null
  },
  {
    "line": 22,
    "token": 425,
    "index": 10,
    "confidence": 0.0,
    "severity": null
  },
  {
    "line": 22,
    "token": 62,
    "index": 11,
    "confidence": 0.0,
    "severity": null
  },
  {
    "line": 22,
    "token": 11250,
    "index": 12,
    "confidence": 0.0,
    "severity": null
  },
  {
    "line": 22,
    "token": 62,
    "index": 13,
    "confidence": 0.0,
    "severity": null
  },
  {
    "line": 22,
    "token": 48610,
    "index": 14,
    "confidence": 0.0,
    "severity": null
  },
  {
    "line": 22,
    "token": 1330,
    "index": 15,
    "confidence": 0.0,
    "severity": null
  },
  {
    "line": 22,
    "token": 651,
    "index": 16,
    "confidence": 0.0,
    "severity": null
  },
  {
    "line": 22,
    "token": 62,
    "index": 17,
    "confidence": 0.0,
    "severity": null
  },
  {
    "line": 22,
    "token": 1891,
    "index": 18,
    "confidence": 0.0,
    "severity": null
  },
  {
    "line": 22,
    "token": 9288,
    "index": 19,
    "confidence": 0.0,
    "severity": null
  },
  {
    "line": 22,
    "token": 62,
    "index": 20,
    "confidence": 0.0,
    "severity": null
  },
  {
    "line": 22,
    "token": 11250,
    "index": 21,
    "confidence": 0.0,
    "severity": null
  },
  {
    "line": 22,
    "token": 62,
    "index": 22,
    "confidence": 0.0,
    "severity": null
  },
  {
    "line": 22,
    "token": 6738,
    "index": 23,
    "confidence": 0.0,
    "severity": null
  },
  {
    "line": 22,
    "token": 7753,
    "index": 24,
    "confidence": 0.0,
    "severity": null
  },
  {
    "line": 22,
    "token": 6738,
    "index": 0,
    "confidence": 0.0,
    "severity": null
  },
  {
    "line": 22,
    "token": 10662,
    "index": 1,
    "confidence": 0.0,
    "severity": null
  },
  {
    "line": 22,
    "token": 8019,
    "index": 2,
    "confidence": 0.0,
    "severity": null
  },
  {
    "line": 22,
    "token": 13,
    "index": 3,
    "confidence": 0.0,
    "severity": null
  },
  {
    "line": 22,
    "token": 45895,
    "index": 4,
    "confidence": 0.0,
    "severity": null
  },
  {
    "line": 22,
    "token": 13,
    "index": 5,
    "confidence": 0.0,
    "severity": null
  },
  {
    "line": 22,
    "token": 3642,
    "index": 6,
    "confidence": 0.0,
    "severity": null
  },
  {
    "line": 22,
    "token": 822,
    "index": 7,
    "confidence": 0.0,
    "severity": null
  },
  {
    "line": 22,
    "token": 13,
    "index": 8,
    "confidence": 0.0,
    "severity": null
  },
  {
    "line": 22,
    "token": 2616,
    "index": 9,
    "confidence": 0.0,
    "severity": null
  },
  {
    "line": 22,
    "token": 425,
    "index": 10,
    "confidence": 0.0,
    "severity": null
  },
  {
    "line": 22,
    "token": 62,
    "index": 11,
    "confidence": 0.0,
    "severity": null
  },
  {
    "line": 22,
    "token": 11250,
    "index": 12,
    "confidence": 0.0,
    "severity": null
  },
  {
    "line": 22,
    "token": 62,
    "index": 13,
    "confidence": 0.0,
    "severity": null
  },
  {
    "line": 22,
    "token": 48610,
    "index": 14,
    "confidence": 0.0,
    "severity": null
  },
  {
    "line": 22,
    "token": 1330,
    "index": 15,
    "confidence": 0.0,
    "severity": null
  },
  {
    "line": 22,
    "token": 651,
    "index": 16,
    "confidence": 0.0,
    "severity": null
  },
  {
    "line": 22,
    "token": 62,
    "index": 17,
    "confidence": 0.0,
    "severity": null
  },
  {
    "line": 22,
    "token": 1891,
    "index": 18,
    "confidence": 0.0,
    "severity": null
  },
  {
    "line": 22,
    "token": 9288,
    "index": 19,
    "confidence": 0.0,
    "severity": null
  },
  {
    "line": 22,
    "token": 62,
    "index": 20,
    "confidence": 0.0,
    "severity": null
  },
  {
    "line": 22,
    "token": 11250,
    "index": 21,
    "confidence": 0.0,
    "severity": null
  },
  {
    "line": 22,
    "token": 62,
    "index": 22,
    "confidence": 0.0,
    "severity": null
  },
  {
    "line": 22,
    "token": 6738,
    "index": 23,
    "confidence": 0.0,
    "severity": null
  },
  {
    "line": 22,
    "token": 7753,
    "index": 24,
    "confidence": 0.0,
    "severity": null
  },
  {
    "line": 39,
    "token": 220,
    "index": 0,
    "confidence": 0.0,
    "severity": null
  },
  {
    "line": 39,
    "token": 220,
    "index": 1,
    "confidence": 0.0,
    "severity": null
  },
  {
    "line": 39,
    "token": 220,
    "index": 2,
    "confidence": 0.0,
    "severity": null
  },
  {
    "line": 39,
    "token": 220,
    "index": 3,
    "confidence": 0.0,
    "severity": null
  },
  {
    "line": 39,
    "token": 220,
    "index": 4,
    "confidence": 0.0,
    "severity": null
  },
  {
    "line": 39,
    "token": 220,
    "index": 5,
    "confidence": 0.0,
    "severity": null
  },
  {
    "line": 39,
    "token": 220,
    "index": 6,
    "confidence": 0.0,
    "severity": null
  },
  {
    "line": 39,
    "token": 220,
    "index": 7,
    "confidence": 0.0,
    "severity": null
  },
  {
    "line": 39,
    "token": 220,
    "index": 8,
    "confidence": 0.0,
    "severity": null
  },
  {
    "line": 39,
    "token": 220,
    "index": 9,
    "confidence": 0.0,
    "severity": null
  },
  {
    "line": 39,
    "token": 220,
    "index": 10,
    "confidence": 0.0,
    "severity": null
  },
  {
    "line": 39,
    "token": 366,
    "index": 11,
    "confidence": 0.0,
    "severity": null
  },
  {
    "line": 39,
    "token": 2435,
    "index": 12,
    "confidence": 0.0,
    "severity": null
  },
  {
    "line": 39,
    "token": 62,
    "index": 13,
    "confidence": 0.0,
    "severity": null
  },
  {
    "line": 39,
    "token": 525,
    "index": 14,
    "confidence": 0.0,
    "severity": null
  },
  {
    "line": 39,
    "token": 62,
    "index": 15,
    "confidence": 0.0,
    "severity": null
  },
  {
    "line": 39,
    "token": 9662,
    "index": 16,
    "confidence": 0.0,
    "severity": null
  },
  {
    "line": 39,
    "token": 1298,
    "index": 17,
    "confidence": 0.0,
    "severity": null
  },
  {
    "line": 39,
    "token": 1366,
    "index": 18,
    "confidence": 0.0,
    "severity": null
  },
  {
    "line": 39,
    "token": 62,
    "index": 19,
    "confidence": 0.0,
    "severity": null
  },
  {
    "line": 39,
    "token": 46324,
    "index": 20,
    "confidence": 0.0,
    "severity": null
  },
  {
    "line": 39,
    "token": 33737,
    "index": 21,
    "confidence": 0.0,
    "severity": null
  },
  {
    "line": 39,
    "token": 11,
    "index": 22,
    "confidence": 0.0,
    "severity": null
  },
  {
    "line": 42,
    "token": 220,
    "index": 0,
    "confidence": 0.0,
    "severity": null
  },
  {
    "line": 42,
    "token": 220,
    "index": 1,
    "confidence": 0.0,
    "severity": null
  },
  {
    "line": 42,
    "token": 220,
    "index": 2,
    "confidence": 0.0,
    "severity": null
  },
  {
    "line": 42,
    "token": 220,
    "index": 3,
    "confidence": 0.0,
    "severity": null
  },
  {
    "line": 42,
    "token": 220,
    "index": 4,
    "confidence": 0.0,
    "severity": null
  },
  {
    "line": 42,
    "token": 220,
    "index": 5,
    "confidence": 0.0,
    "severity": null
  },
  {
    "line": 42,
    "token": 220,
    "index": 6,
    "confidence": 0.0,
    "severity": null
  },
  {
    "line": 42,
    "token": 220,
    "index": 7,
    "confidence": 0.0,
    "severity": null
  },
  {
    "line": 42,
    "token": 220,
    "index": 8,
    "confidence": 0.0,
    "severity": null
  },
  {
    "line": 42,
    "token": 220,
    "index": 9,
    "confidence": 0.0,
    "severity": null
  },
  {
    "line": 42,
    "token": 220,
    "index": 10,
    "confidence": 0.0,
    "severity": null
  },
  {
    "line": 42,
    "token": 366,
    "index": 11,
    "confidence": 0.0,
    "severity": null
  },
  {
    "line": 42,
    "token": 8612,
    "index": 12,
    "confidence": 0.0,
    "severity": null
  },
  {
    "line": 42,
    "token": 378,
    "index": 13,
    "confidence": 0.0,
    "severity": null
  },
  {
    "line": 42,
    "token": 62,
    "index": 14,
    "confidence": 0.0,
    "severity": null
  },
  {
    "line": 42,
    "token": 13116,
    "index": 15,
    "confidence": 0.0,
    "severity": null
  },
  {
    "line": 42,
    "token": 1298,
    "index": 16,
    "confidence": 0.0,
    "severity": null
  },
  {
    "line": 42,
    "token": 7716,
    "index": 17,
    "confidence": 0.0,
    "severity": null
  },
  {
    "line": 42,
    "token": 62,
    "index": 18,
    "confidence": 0.0,
    "severity": null
  },
  {
    "line": 42,
    "token": 13116,
    "index": 19,
    "confidence": 0.0,
    "severity": null
  },
  {
    "line": 42,
    "token": 11,
    "index": 20,
    "confidence": 0.0,
    "severity": null
  },
  {
    "line": 53,
    "token": 220,
    "index": 0,
    "confidence": 0.0,
    "severity": null
  },
  {
    "line": 53,
    "token": 220,
    "index": 1,
    "confidence": 0.0,
    "severity": null
  },
  {
    "line": 53,
    "token": 220,
    "index": 2,
    "confidence": 0.0,
    "severity": null
  },
  {
    "line": 53,
    "token": 220,
    "index": 3,
    "confidence": 0.0,
    "severity": null
  },
  {
    "line": 53,
    "token": 220,
    "index": 4,
    "confidence": 0.0,
    "severity": null
  },
  {
    "line": 53,
    "token": 220,
    "index": 5,
    "confidence": 0.0,
    "severity": null
  },
  {
    "line": 53,
    "token": 220,
    "index": 6,
    "confidence": 0.0,
    "severity": null
  },
  {
    "line": 53,
    "token": 220,
    "index": 7,
    "confidence": 0.0,
    "severity": null
  },
  {
    "line": 53,
    "token": 220,
    "index": 8,
    "confidence": 0.0,
    "severity": null
  },
  {
    "line": 53,
    "token": 220,
    "index": 9,
    "confidence": 0.0,
    "severity": null
  },
  {
    "line": 53,
    "token": 220,
    "index": 10,
    "confidence": 0.0,
    "severity": null
  },
  {
    "line": 53,
    "token": 366,
    "index": 11,
    "confidence": 0.0,
    "severity": null
  },
  {
    "line": 53,
    "token": 46265,
    "index": 12,
    "confidence": 0.0,
    "severity": null
  },
  {
    "line": 53,
    "token": 22046,
    "index": 13,
    "confidence": 0.0,
    "severity": null
  },
  {
    "line": 53,
    "token": 1298,
    "index": 14,
    "confidence": 0.0,
    "severity": null
  },
  {
    "line": 53,
    "token": 1391,
    "index": 15,
    "confidence": 0.0,
    "severity": null
  },
  {
    "line": 57,
    "token": 220,
    "index": 0,
    "confidence": 0.0,
    "severity": null
  },
  {
    "line": 57,
    "token": 220,
    "index": 1,
    "confidence": 0.0,
    "severity": null
  },
  {
    "line": 57,
    "token": 220,
    "index": 2,
    "confidence": 0.0,
    "severity": null
  },
  {
    "line": 57,
    "token": 220,
    "index": 3,
    "confidence": 0.0,
    "severity": null
  },
  {
    "line": 57,
    "token": 220,
    "index": 4,
    "confidence": 0.0,
    "severity": null
  },
  {
    "line": 57,
    "token": 220,
    "index": 5,
    "confidence": 0.0,
    "severity": null
  },
  {
    "line": 57,
    "token": 220,
    "index": 6,
    "confidence": 0.0,
    "severity": null
  },
  {
    "line": 57,
    "token": 220,
    "index": 7,
    "confidence": 0.0,
    "severity": null
  },
  {
    "line": 57,
    "token": 220,
    "index": 8,
    "confidence": 0.0,
    "severity": null
  },
  {
    "line": 57,
    "token": 220,
    "index": 9,
    "confidence": 0.0,
    "severity": null
  },
  {
    "line": 57,
    "token": 220,
    "index": 10,
    "confidence": 0.0,
    "severity": null
  },
  {
    "line": 57,
    "token": 220,
    "index": 11,
    "confidence": 0.0,
    "severity": null
  },
  {
    "line": 57,
    "token": 220,
    "index": 12,
    "confidence": 0.0,
    "severity": null
  },
  {
    "line": 57,
    "token": 220,
    "index": 13,
    "confidence": 0.0,
    "severity": null
  },
  {
    "line": 57,
    "token": 220,
    "index": 14,
    "confidence": 0.0,
    "severity": null
  },
  {
    "line": 57,
    "token": 366,
    "index": 15,
    "confidence": 0.0,
    "severity": null
  },
  {
    "line": 57,
    "token": 11659,
    "index": 16,
    "confidence": 0.0,
    "severity": null
  },
  {
    "line": 57,
    "token": 62,
    "index": 17,
    "confidence": 0.0,
    "severity": null
  },
  {
    "line": 57,
    "token": 7890,
    "index": 18,
    "confidence": 0.0,
    "severity": null
  },
  {
    "line": 57,
    "token": 1298,
    "index": 19,
    "confidence": 0.0,
    "severity": null
  },
  {
    "line": 57,
    "token": 6407,
    "index": 20,
    "confidence": 0.0,
    "severity": null
  },
  {
    "line": 57,
    "token": 11,
    "index": 21,
    "confidence": 0.0,
    "severity": null
  },
  {
    "line": 59,
    "token": 220,
    "index": 0,
    "confidence": 0.0,
    "severity": null
  },
  {
    "line": 59,
    "token": 220,
    "index": 1,
    "confidence": 0.0,
    "severity": null
  },
  {
    "line": 59,
    "token": 220,
    "index": 2,
    "confidence": 0.0,
    "severity": null
  },
  {
    "line": 59,
    "token": 220,
    "index": 3,
    "confidence": 0.0,
    "severity": null
  },
  {
    "line": 59,
    "token": 220,
    "index": 4,
    "confidence": 0.0,
    "severity": null
  },
  {
    "line": 59,
    "token": 220,
    "index": 5,
    "confidence": 0.0,
    "severity": null
  },
  {
    "line": 59,
    "token": 220,
    "index": 6,
    "confidence": 0.0,
    "severity": null
  },
  {
    "line": 59,
    "token": 1782,
    "index": 7,
    "confidence": 0.0,
    "severity": null
  },
  {
    "line": 61,
    "token": 220,
    "index": 0,
    "confidence": 0.0,
    "severity": null
  },
  {
    "line": 61,
    "token": 220,
    "index": 1,
    "confidence": 0.0,
    "severity": null
  },
  {
    "line": 61,
    "token": 220,
    "index": 2,
    "confidence": 0.0,
    "severity": null
  },
  {
    "line": 61,
    "token": 1441,
    "index": 3,
    "confidence": 0.0,
    "severity": null
  },
  {
    "line": 61,
    "token": 3121,
    "index": 4,
    "confidence": 0.0,
    "severity": null
  },
  {
    "line": 61,
    "token": 273,
    "index": 5,
    "confidence": 0.0,
    "severity": null
  },
  {
    "line": 61,
    "token": 62,
    "index": 6,
    "confidence": 0.0,
    "severity": null
  },
  {
    "line": 61,
    "token": 11250,
    "index": 7,
    "confidence": 0.0,
    "severity": null
  },
  {
    "line": 67,
    "token": 220,
    "index": 0,
    "confidence": 0.0,
    "severity": null
  },
  {
    "line": 67,
    "token": 220,
    "index": 1,
    "confidence": 0.0,
    "severity": null
  },
  {
    "line": 67,
    "token": 220,
    "index": 2,
    "confidence": 0.0,
    "severity": null
  },
  {
    "line": 67,
    "token": 220,
    "index": 3,
    "confidence": 0.0,
    "severity": null
  },
  {
    "line": 67,
    "token": 220,
    "index": 4,
    "confidence": 0.0,
    "severity": null
  },
  {
    "line": 67,
    "token": 220,
    "index": 5,
    "confidence": 0.0,
    "severity": null
  },
  {
    "line": 67,
    "token": 220,
    "index": 6,
    "confidence": 0.0,
    "severity": null
  },
  {
    "line": 67,
    "token": 611,
    "index": 7,
    "confidence": 0.0,
    "severity": null
  },
  {
    "line": 67,
    "token": 318,
    "index": 8,
    "confidence": 0.0,
    "severity": null
  },
  {
    "line": 67,
    "token": 39098,
    "index": 9,
    "confidence": 0.0,
    "severity": null
  },
  {
    "line": 67,
    "token": 7,
    "index": 10,
    "confidence": 0.0,
    "severity": null
  },
  {
    "line": 67,
    "token": 8367,
    "index": 11,
    "confidence": 0.0,
    "severity": null
  },
  {
    "line": 67,
    "token": 62,
    "index": 12,
    "confidence": 0.0,
    "severity": null
  },
  {
    "line": 67,
    "token": 11600,
    "index": 13,
    "confidence": 0.0,
    "severity": null
  },
  {
    "line": 67,
    "token": 11,
    "index": 14,
    "confidence": 0.0,
    "severity": null
  },
  {
    "line": 67,
    "token": 7308,
    "index": 15,
    "confidence": 0.0,
    "severity": null
  },
  {
    "line": 67,
    "token": 18743,
    "index": 16,
    "confidence": 0.0,
    "severity": null
  },
  {
    "line": 67,
    "token": 5497,
    "index": 17,
    "confidence": 0.0,
    "severity": null
  },
  {
    "line": 67,
    "token": 26407,
    "index": 18,
    "confidence": 0.0,
    "severity": null
  },
  {
    "line": 67,
    "token": 2599,
    "index": 19,
    "confidence": 0.0,
    "severity": null
  },
  {
    "line": 69,
    "token": 220,
    "index": 0,
    "confidence": 0.0,
    "severity": null
  },
  {
    "line": 69,
    "token": 220,
    "index": 1,
    "confidence": 0.0,
    "severity": null
  },
  {
    "line": 69,
    "token": 220,
    "index": 2,
    "confidence": 0.0,
    "severity": null
  },
  {
    "line": 69,
    "token": 220,
    "index": 3,
    "confidence": 0.0,
    "severity": null
  },
  {
    "line": 69,
    "token": 220,
    "index": 4,
    "confidence": 0.0,
    "severity": null
  },
  {
    "line": 69,
    "token": 220,
    "index": 5,
    "confidence": 0.0,
    "severity": null
  },
  {
    "line": 69,
    "token": 220,
    "index": 6,
    "confidence": 0.0,
    "severity": null
  },
  {
    "line": 69,
    "token": 220,
    "index": 7,
    "confidence": 0.0,
    "severity": null
  },
  {
    "line": 69,
    "token": 220,
    "index": 8,
    "confidence": 0.0,
    "severity": null
  },
  {
    "line": 69,
    "token": 220,
    "index": 9,
    "confidence": 0.0,
    "severity": null
  },
  {
    "line": 69,
    "token": 220,
    "index": 10,
    "confidence": 0.0,
    "severity": null
  },
  {
    "line": 69,
    "token": 1988,
    "index": 11,
    "confidence": 0.0,
    "severity": null
  },
  {
    "line": 69,
    "token": 62,
    "index": 12,
    "confidence": 0.0,
    "severity": null
  },
  {
    "line": 69,
    "token": 11600,
    "index": 13,
    "confidence": 0.0,
    "severity": null
  },
  {
    "line": 69,
    "token": 796,
    "index": 14,
    "confidence": 0.0,
    "severity": null
  },
  {
    "line": 69,
    "token": 1988,
    "index": 15,
    "confidence": 0.0,
    "severity": null
  },
  {
    "line": 69,
    "token": 62,
    "index": 16,
    "confidence": 0.0,
    "severity": null
  },
  {
    "line": 69,
    "token": 11600,
    "index": 17,
    "confidence": 0.0,
    "severity": null
  },
  {
    "line": 69,
    "token": 13,
    "index": 18,
    "confidence": 0.0,
    "severity": null
  },
  {
    "line": 69,
    "token": 1462,
    "index": 19,
    "confidence": 0.0,
    "severity": null
  },
  {
    "line": 69,
    "token": 62,
    "index": 20,
    "confidence": 0.0,
    "severity": null
  },
  {
    "line": 69,
    "token": 25076,
    "index": 21,
    "confidence": 0.0,
    "severity": null
  },
  {
    "line": 69,
    "token": 3419,
    "index": 22,
    "confidence": 0.0,
    "severity": null
  },
  {
    "line": 76,
    "token": 220,
    "index": 0,
    "confidence": 0.0,
    "severity": null
  },
  {
    "line": 76,
    "token": 220,
    "index": 1,
    "confidence": 0.0,
    "severity": null
  },
  {
    "line": 76,
    "token": 220,
    "index": 2,
    "confidence": 0.0,
    "severity": null
  },
  {
    "line": 76,
    "token": 220,
    "index": 3,
    "confidence": 0.0,
    "severity": null
  },
  {
    "line": 76,
    "token": 220,
    "index": 4,
    "confidence": 0.0,
    "severity": null
  },
  {
    "line": 76,
    "token": 220,
    "index": 5,
    "confidence": 0.0,
    "severity": null
  },
  {
    "line": 76,
    "token": 220,
    "index": 6,
    "confidence": 0.0,
    "severity": null
  },
  {
    "line": 76,
    "token": 1988,
    "index": 7,
    "confidence": 0.0,
    "severity": null
  },
  {
    "line": 76,
    "token": 62,
    "index": 8,
    "confidence": 0.0,
    "severity": null
  },
  {
    "line": 76,
    "token": 11600,
    "index": 9,
    "confidence": 0.0,
    "severity": null
  },
  {
    "line": 76,
    "token": 796,
    "index": 10,
    "confidence": 0.0,
    "severity": null
  },
  {
    "line": 76,
    "token": 279,
    "index": 11,
    "confidence": 0.0,
    "severity": null
  },
  {
    "line": 76,
    "token": 67,
    "index": 12,
    "confidence": 0.0,
    "severity": null
  },
  {
    "line": 76,
    "token": 13,
    "index": 13,
    "confidence": 0.0,
    "severity": null
  },
  {
    "line": 76,
    "token": 6601,
    "index": 14,
    "confidence": 0.0,
    "severity": null
  },
  {
    "line": 76,
    "token": 19778,
    "index": 15,
    "confidence": 0.0,
    "severity": null
  },
  {
    "line": 76,
    "token": 7,
    "index": 16,
    "confidence": 0.0,
    "severity": null
  },
  {
    "line": 76,
    "token": 8367,
    "index": 17,
    "confidence": 0.0,
    "severity": null
  },
  {
    "line": 76,
    "token": 62,
    "index": 18,
    "confidence": 0.0,
    "severity": null
  },
  {
    "line": 76,
    "token": 11600,
    "index": 19,
    "confidence": 0.0,
    "severity": null
  },
  {
    "line": 76,
    "token": 8,
    "index": 20,
    "confidence": 0.0,
    "severity": null
  },
  {
    "line": 76,
    "token": 220,
    "index": 0,
    "confidence": 0.0,
    "severity": null
  },
  {
    "line": 76,
    "token": 220,
    "index": 1,
    "confidence": 0.0,
    "severity": null
  },
  {
    "line": 76,
    "token": 220,
    "index": 2,
    "confidence": 0.0,
    "severity": null
  },
  {
    "line": 76,
    "token": 220,
    "index": 3,
    "confidence": 0.0,
    "severity": null
  },
  {
    "line": 76,
    "token": 220,
    "index": 4,
    "confidence": 0.0,
    "severity": null
  },
  {
    "line": 76,
    "token": 220,
    "index": 5,
    "confidence": 0.0,
    "severity": null
  },
  {
    "line": 76,
    "token": 220,
    "index": 6,
    "confidence": 0.0,
    "severity": null
  },
  {
    "line": 76,
    "token": 1988,
    "index": 7,
    "confidence": 0.0,
    "severity": null
  },
  {
    "line": 76,
    "token": 62,
    "index": 8,
    "confidence": 0.0,
    "severity": null
  },
  {
    "line": 76,
    "token": 11600,
    "index": 9,
    "confidence": 0.0,
    "severity": null
  },
  {
    "line": 76,
    "token": 796,
    "index": 10,
    "confidence": 0.0,
    "severity": null
  },
  {
    "line": 76,
    "token": 279,
    "index": 11,
    "confidence": 0.0,
    "severity": null
  },
  {
    "line": 76,
    "token": 67,
    "index": 12,
    "confidence": 0.0,
    "severity": null
  },
  {
    "line": 76,
    "token": 13,
    "index": 13,
    "confidence": 0.0,
    "severity": null
  },
  {
    "line": 76,
    "token": 6601,
    "index": 14,
    "confidence": 0.0,
    "severity": null
  },
  {
    "line": 76,
    "token": 19778,
    "index": 15,
    "confidence": 0.0,
    "severity": null
  },
  {
    "line": 76,
    "token": 7,
    "index": 16,
    "confidence": 0.0,
    "severity": null
  },
  {
    "line": 76,
    "token": 8367,
    "index": 17,
    "confidence": 0.0,
    "severity": null
  },
  {
    "line": 76,
    "token": 62,
    "index": 18,
    "confidence": 0.0,
    "severity": null
  },
  {
    "line": 76,
    "token": 11600,
    "index": 19,
    "confidence": 0.0,
    "severity": null
  },
  {
    "line": 76,
    "token": 8,
    "index": 20,
    "confidence": 0.0,
    "severity": null
  },
  {
    "line": 72,
    "token": 220,
    "index": 0,
    "confidence": 0.0,
    "severity": null
  },
  {
    "line": 72,
    "token": 220,
    "index": 1,
    "confidence": 0.0,
    "severity": null
  },
  {
    "line": 72,
    "token": 220,
    "index": 2,
    "confidence": 0.0,
    "severity": null
  },
  {
    "line": 72,
    "token": 220,
    "index": 3,
    "confidence": 0.0,
    "severity": null
  },
  {
    "line": 72,
    "token": 220,
    "index": 4,
    "confidence": 0.0,
    "severity": null
  },
  {
    "line": 72,
    "token": 220,
    "index": 5,
    "confidence": 0.0,
    "severity": null
  },
  {
    "line": 72,
    "token": 220,
    "index": 6,
    "confidence": 0.0,
    "severity": null
  },
  {
    "line": 72,
    "token": 220,
    "index": 7,
    "confidence": 0.0,
    "severity": null
  },
  {
    "line": 72,
    "token": 220,
    "index": 8,
    "confidence": 0.0,
    "severity": null
  },
  {
    "line": 72,
    "token": 220,
    "index": 9,
    "confidence": 0.0,
    "severity": null
  },
  {
    "line": 72,
    "token": 220,
    "index": 10,
    "confidence": 0.0,
    "severity": null
  },
  {
    "line": 72,
    "token": 611,
    "index": 11,
    "confidence": 0.0,
    "severity": null
  },
  {
    "line": 72,
    "token": 1988,
    "index": 12,
    "confidence": 0.0,
    "severity": null
  },
  {
    "line": 72,
    "token": 62,
    "index": 13,
    "confidence": 0.0,
    "severity": null
  },
  {
    "line": 72,
    "token": 11600,
    "index": 14,
    "confidence": 0.0,
    "severity": null
  },
  {
    "line": 72,
    "token": 14692,
    "index": 15,
    "confidence": 0.0,
    "severity": null
  },
  {
    "line": 72,
    "token": 487,
    "index": 16,
    "confidence": 0.0,
    "severity": null
  },
  {
    "line": 72,
    "token": 81,
    "index": 17,
    "confidence": 0.0,
    "severity": null
  },
  {
    "line": 72,
    "token": 1,
    "index": 18,
    "confidence": 0.0,
    "severity": null
  },
  {
    "line": 72,
    "token": 4083,
    "index": 19,
    "confidence": 0.0,
    "severity": null
  },
  {
    "line": 72,
    "token": 28920,
    "index": 20,
    "confidence": 0.0,
    "severity": null
  },
  {
    "line": 72,
    "token": 25,
    "index": 21,
    "confidence": 0.0,
    "severity": null
  },
  {
    "line": 92,
    "token": 220,
    "index": 0,
    "confidence": 0.0,
    "severity": null
  },
  {
    "line": 92,
    "token": 220,
    "index": 1,
    "confidence": 0.0,
    "severity": null
  },
  {
    "line": 92,
    "token": 220,
    "index": 2,
    "confidence": 0.0,
    "severity": null
  },
  {
    "line": 92,
    "token": 37227,
    "index": 3,
    "confidence": 0.0,
    "severity": null
  },
  {
    "line": 92,
    "token": 8645,
    "index": 4,
    "confidence": 0.0,
    "severity": null
  },
  {
    "line": 92,
    "token": 378,
    "index": 5,
    "confidence": 0.0,
    "severity": null
  },
  {
    "line": 92,
    "token": 736,
    "index": 6,
    "confidence": 0.0,
    "severity": null
  },
  {
    "line": 92,
    "token": 9288,
    "index": 7,
    "confidence": 0.0,
    "severity": null
  },
  {
    "line": 92,
    "token": 3136,
    "index": 8,
    "confidence": 0.0,
    "severity": null
  },
  {
    "line": 96,
    "token": 220,
    "index": 0,
    "confidence": 0.0,
    "severity": null
  },
  {
    "line": 96,
    "token": 220,
    "index": 1,
    "confidence": 0.0,
    "severity": null
  },
  {
    "line": 96,
    "token": 220,
    "index": 2,
    "confidence": 0.0,
    "severity": null
  },
  {
    "line": 96,
    "token": 5370,
    "index": 3,
    "confidence": 0.0,
    "severity": null
  },
  {
    "line": 96,
    "token": 25,
    "index": 4,
    "confidence": 0.0,
    "severity": null
  },
  {
    "line": 99,
    "token": 220,
    "index": 0,
    "confidence": 0.0,
    "severity": null
  },
  {
    "line": 99,
    "token": 220,
    "index": 1,
    "confidence": 0.0,
    "severity": null
  },
  {
    "line": 99,
    "token": 220,
    "index": 2,
    "confidence": 0.0,
    "severity": null
  },
  {
    "line": 99,
    "token": 220,
    "index": 3,
    "confidence": 0.0,
    "severity": null
  },
  {
    "line": 99,
    "token": 220,
    "index": 4,
    "confidence": 0.0,
    "severity": null
  },
  {
    "line": 99,
    "token": 220,
    "index": 5,
    "confidence": 0.0,
    "severity": null
  },
  {
    "line": 99,
    "token": 220,
    "index": 6,
    "confidence": 0.0,
    "severity": null
  },
  {
    "line": 99,
    "token": 7343,
    "index": 7,
    "confidence": 0.0,
    "severity": null
  },
  {
    "line": 99,
    "token": 286,
    "index": 8,
    "confidence": 0.0,
    "severity": null
  },
  {
    "line": 99,
    "token": 16916,
    "index": 9,
    "confidence": 0.0,
    "severity": null
  },
  {
    "line": 99,
    "token": 3136,
    "index": 10,
    "confidence": 0.0,
    "severity": null
  },
  {
    "line": 99,
    "token": 13,
    "index": 11,
    "confidence": 0.0,
    "severity": null
  },
  {
    "line": 103,
    "token": 220,
    "index": 0,
    "confidence": 0.0,
    "severity": null
  },
  {
    "line": 103,
    "token": 220,
    "index": 1,
    "confidence": 0.0,
    "severity": null
  },
  {
    "line": 103,
    "token": 220,
    "index": 2,
    "confidence": 0.0,
    "severity": null
  },
  {
    "line": 103,
    "token": 37227,
    "index": 3,
    "confidence": 0.0,
    "severity": null
  },
  {
    "line": 107,
    "token": 220,
    "index": 0,
    "confidence": 0.0,
    "severity": null
  },
  {
    "line": 107,
    "token": 220,
    "index": 1,
    "confidence": 0.0,
    "severity": null
  },
  {
    "line": 107,
    "token": 220,
    "index": 2,
    "confidence": 0.0,
    "severity": null
  },
  {
    "line": 107,
    "token": 329,
    "index": 3,
    "confidence": 0.0,
    "severity": null
  },
  {
    "line": 107,
    "token": 989,
    "index": 4,
    "confidence": 0.0,
    "severity": null
  },
  {
    "line": 107,
    "token": 62,
    "index": 5,
    "confidence": 0.0,
    "severity": null
  },
  {
    "line": 107,
    "token": 521,
    "index": 6,
    "confidence": 0.0,
    "severity": null
  },
  {
    "line": 107,
    "token": 26407,
    "index": 7,
    "confidence": 0.0,
    "severity": null
  },
  {
    "line": 107,
    "token": 287,
    "index": 8,
    "confidence": 0.0,
    "severity": null
  },
  {
    "line": 107,
    "token": 989,
    "index": 9,
    "confidence": 0.0,
    "severity": null
  },
  {
    "line": 107,
    "token": 62,
    "index": 10,
    "confidence": 0.0,
    "severity": null
  },
  {
    "line": 107,
    "token": 521,
    "index": 11,
    "confidence": 0.0,
    "severity": null
  },
  {
    "line": 107,
    "token": 44549,
    "index": 12,
    "confidence": 0.0,
    "severity": null
  },
  {
    "line": 107,
    "token": 25,
    "index": 13,
    "confidence": 0.0,
    "severity": null
  },
  {
    "line": 132,
    "token": 220,
    "index": 0,
    "confidence": 0.0,
    "severity": null
  },
  {
    "line": 132,
    "token": 220,
    "index": 1,
    "confidence": 0.0,
    "severity": null
  },
  {
    "line": 132,
    "token": 220,
    "index": 2,
    "confidence": 0.0,
    "severity": null
  },
  {
    "line": 132,
    "token": 7716,
    "index": 3,
    "confidence": 0.0,
    "severity": null
  },
  {
    "line": 132,
    "token": 62,
    "index": 4,
    "confidence": 0.0,
    "severity": null
  },
  {
    "line": 132,
    "token": 13116,
    "index": 5,
    "confidence": 0.0,
    "severity": null
  },
  {
    "line": 132,
    "token": 25,
    "index": 6,
    "confidence": 0.0,
    "severity": null
  },
  {
    "line": 132,
    "token": 20512,
    "index": 7,
    "confidence": 0.0,
    "severity": null
  },
  {
    "line": 132,
    "token": 796,
    "index": 8,
    "confidence": 0.0,
    "severity": null
  },
  {
    "line": 132,
    "token": 10352,
    "index": 9,
    "confidence": 0.0,
    "severity": null
  },
  {
    "line": 132,
    "token": 11,
    "index": 10,
    "confidence": 0.0,
    "severity": null
  },
  {
    "line": 134,
    "token": 220,
    "index": 0,
    "confidence": 0.0,
    "severity": null
  },
  {
    "line": 134,
    "token": 220,
    "index": 1,
    "confidence": 0.0,
    "severity": null
  },
  {
    "line": 134,
    "token": 220,
    "index": 2,
    "confidence": 0.0,
    "severity": null
  },
  {
    "line": 134,
    "token": 37227,
    "index": 3,
    "confidence": 0.0,
    "severity": null
  },
  {
    "line": 134,
    "token": 10987,
    "index": 4,
    "confidence": 0.0,
    "severity": null
  },
  {
    "line": 134,
    "token": 736,
    "index": 5,
    "confidence": 0.0,
    "severity": null
  },
  {
    "line": 134,
    "token": 9288,
    "index": 6,
    "confidence": 0.0,
    "severity": null
  },
  {
    "line": 134,
    "token": 287,
    "index": 7,
    "confidence": 0.0,
    "severity": null
  },
  {
    "line": 134,
    "token": 257,
    "index": 8,
    "confidence": 0.0,
    "severity": null
  },
  {
    "line": 134,
    "token": 2060,
    "index": 9,
    "confidence": 0.0,
    "severity": null
  },
  {
    "line": 134,
    "token": 4704,
    "index": 10,
    "confidence": 0.0,
    "severity": null
  },
  {
    "line": 134,
    "token": 351,
    "index": 11,
    "confidence": 0.0,
    "severity": null
  },
  {
    "line": 134,
    "token": 14206,
    "index": 12,
    "confidence": 0.0,
    "severity": null
  },
  {
    "line": 134,
    "token": 45869,
    "index": 13,
    "confidence": 0.0,
    "severity": null
  },
  {
    "line": 134,
    "token": 18743,
    "index": 14,
    "confidence": 0.0,
    "severity": null
  },
  {
    "line": 134,
    "token": 23002,
    "index": 15,
    "confidence": 0.0,
    "severity": null
  },
  {
    "line": 134,
    "token": 1009,
    "index": 16,
    "confidence": 0.0,
    "severity": null
  },
  {
    "line": 134,
    "token": 35375,
    "index": 17,
    "confidence": 0.0,
    "severity": null
  },
  {
    "line": 134,
    "token": 13,
    "index": 18,
    "confidence": 0.0,
    "severity": null
  },
  {
    "line": 134,
    "token": 383,
    "index": 19,
    "confidence": 0.0,
    "severity": null
  },
  {
    "line": 134,
    "token": 6266,
    "index": 20,
    "confidence": 0.0,
    "severity": null
  },
  {
    "line": 134,
    "token": 481,
    "index": 21,
    "confidence": 0.0,
    "severity": null
  },
  {
    "line": 134,
    "token": 307,
    "index": 22,
    "confidence": 0.0,
    "severity": null
  },
  {
    "line": 134,
    "token": 10945,
    "index": 23,
    "confidence": 0.0,
    "severity": null
  },
  {
    "line": 134,
    "token": 1110,
    "index": 24,
    "confidence": 0.0,
    "severity": null
  },
  {
    "line": 134,
    "token": 416,
    "index": 25,
    "confidence": 0.0,
    "severity": null
  },
  {
    "line": 134,
    "token": 1110,
    "index": 26,
    "confidence": 0.0,
    "severity": null
  },
  {
    "line": 134,
    "token": 13,
    "index": 27,
    "confidence": 0.0,
    "severity": null
  },
  {
    "line": 138,
    "token": 220,
    "index": 0,
    "confidence": 0.0,
    "severity": null
  },
  {
    "line": 138,
    "token": 220,
    "index": 1,
    "confidence": 0.0,
    "severity": null
  },
  {
    "line": 138,
    "token": 220,
    "index": 2,
    "confidence": 0.0,
    "severity": null
  },
  {
    "line": 138,
    "token": 24200,
    "index": 3,
    "confidence": 0.0,
    "severity": null
  },
  {
    "line": 138,
    "token": 438,
    "index": 4,
    "confidence": 0.0,
    "severity": null
  },
  {
    "line": 140,
    "token": 220,
    "index": 0,
    "confidence": 0.0,
    "severity": null
  },
  {
    "line": 140,
    "token": 220,
    "index": 1,
    "confidence": 0.0,
    "severity": null
  },
  {
    "line": 140,
    "token": 220,
    "index": 2,
    "confidence": 0.0,
    "severity": null
  },
  {
    "line": 140,
    "token": 220,
    "index": 3,
    "confidence": 0.0,
    "severity": null
  },
  {
    "line": 140,
    "token": 220,
    "index": 4,
    "confidence": 0.0,
    "severity": null
  },
  {
    "line": 140,
    "token": 220,
    "index": 5,
    "confidence": 0.0,
    "severity": null
  },
  {
    "line": 140,
    "token": 220,
    "index": 6,
    "confidence": 0.0,
    "severity": null
  },
  {
    "line": 140,
    "token": 5157,
    "index": 7,
    "confidence": 0.0,
    "severity": null
  },
  {
    "line": 140,
    "token": 9288,
    "index": 8,
    "confidence": 0.0,
    "severity": null
  },
  {
    "line": 140,
    "token": 4566,
    "index": 9,
    "confidence": 0.0,
    "severity": null
  },
  {
    "line": 140,
    "token": 220,
    "index": 0,
    "confidence": 0.0,
    "severity": null
  },
  {
    "line": 140,
    "token": 220,
    "index": 1,
    "confidence": 0.0,
    "severity": null
  },
  {
    "line": 140,
    "token": 220,
    "index": 2,
    "confidence": 0.0,
    "severity": null
  },
  {
    "line": 140,
    "token": 220,
    "index": 3,
    "confidence": 0.0,
    "severity": null
  },
  {
    "line": 140,
    "token": 220,
    "index": 4,
    "confidence": 0.0,
    "severity": null
  },
  {
    "line": 140,
    "token": 220,
    "index": 5,
    "confidence": 0.0,
    "severity": null
  },
  {
    "line": 140,
    "token": 220,
    "index": 6,
    "confidence": 0.0,
    "severity": null
  },
  {
    "line": 140,
    "token": 5157,
    "index": 7,
    "confidence": 0.0,
    "severity": null
  },
  {
    "line": 140,
    "token": 9288,
    "index": 8,
    "confidence": 0.0,
    "severity": null
  },
  {
    "line": 140,
    "token": 4566,
    "index": 9,
    "confidence": 0.0,
    "severity": null
  },
  {
    "line": 147,
    "token": 220,
    "index": 0,
    "confidence": 0.0,
    "severity": null
  },
  {
    "line": 147,
    "token": 220,
    "index": 1,
    "confidence": 0.0,
    "severity": null
  },
  {
    "line": 147,
    "token": 220,
    "index": 2,
    "confidence": 0.0,
    "severity": null
  },
  {
    "line": 147,
    "token": 6626,
    "index": 3,
    "confidence": 0.0,
    "severity": null
  },
  {
    "line": 160,
    "token": 220,
    "index": 0,
    "confidence": 0.0,
    "severity": null
  },
  {
    "line": 160,
    "token": 220,
    "index": 1,
    "confidence": 0.0,
    "severity": null
  },
  {
    "line": 160,
    "token": 220,
    "index": 2,
    "confidence": 0.0,
    "severity": null
  },
  {
    "line": 160,
    "token": 14420,
    "index": 3,
    "confidence": 0.0,
    "severity": null
  },
  {
    "line": 160,
    "token": 796,
    "index": 4,
    "confidence": 0.0,
    "severity": null
  },
  {
    "line": 160,
    "token": 6266,
    "index": 5,
    "confidence": 0.0,
    "severity": null
  },
  {
    "line": 160,
    "token": 13,
    "index": 6,
    "confidence": 0.0,
    "severity": null
  },
  {
    "line": 160,
    "token": 259,
    "index": 7,
    "confidence": 0.0,
    "severity": null
  },
  {
    "line": 160,
    "token": 43872,
    "index": 8,
    "confidence": 0.0,
    "severity": null
  },
  {
    "line": 160,
    "token": 13,
    "index": 9,
    "confidence": 0.0,
    "severity": null
  },
  {
    "line": 160,
    "token": 34642,
    "index": 10,
    "confidence": 0.0,
    "severity": null
  },
  {
    "line": 160,
    "token": 22446,
    "index": 11,
    "confidence": 0.0,
    "severity": null
  },
  {
    "line": 160,
    "token": 83,
    "index": 12,
    "confidence": 0.0,
    "severity": null
  },
  {
    "line": 160,
    "token": 349,
    "index": 13,
    "confidence": 0.0,
    "severity": null
  },
  {
    "line": 160,
    "token": 396,
    "index": 14,
    "confidence": 0.0,
    "severity": null
  },
  {
    "line": 160,
    "token": 3419,
    "index": 15,
    "confidence": 0.0,
    "severity": null
  },
  {
    "line": 160,
    "token": 220,
    "index": 0,
    "confidence": 0.0,
    "severity": null
  },
  {
    "line": 160,
    "token": 220,
    "index": 1,
    "confidence": 0.0,
    "severity": null
  },
  {
    "line": 160,
    "token": 220,
    "index": 2,
    "confidence": 0.0,
    "severity": null
  },
  {
    "line": 160,
    "token": 14420,
    "index": 3,
    "confidence": 0.0,
    "severity": null
  },
  {
    "line": 160,
    "token": 796,
    "index": 4,
    "confidence": 0.0,
    "severity": null
  },
  {
    "line": 160,
    "token": 6266,
    "index": 5,
    "confidence": 0.0,
    "severity": null
  },
  {
    "line": 160,
    "token": 13,
    "index": 6,
    "confidence": 0.0,
    "severity": null
  },
  {
    "line": 160,
    "token": 259,
    "index": 7,
    "confidence": 0.0,
    "severity": null
  },
  {
    "line": 160,
    "token": 43872,
    "index": 8,
    "confidence": 0.0,
    "severity": null
  },
  {
    "line": 160,
    "token": 13,
    "index": 9,
    "confidence": 0.0,
    "severity": null
  },
  {
    "line": 160,
    "token": 34642,
    "index": 10,
    "confidence": 0.0,
    "severity": null
  },
  {
    "line": 160,
    "token": 22446,
    "index": 11,
    "confidence": 0.0,
    "severity": null
  },
  {
    "line": 160,
    "token": 83,
    "index": 12,
    "confidence": 0.0,
    "severity": null
  },
  {
    "line": 160,
    "token": 349,
    "index": 13,
    "confidence": 0.0,
    "severity": null
  },
  {
    "line": 160,
    "token": 396,
    "index": 14,
    "confidence": 0.0,
    "severity": null
  },
  {
    "line": 160,
    "token": 3419,
    "index": 15,
    "confidence": 0.0,
    "severity": null
  },
  {
    "line": 169,
    "token": 220,
    "index": 0,
    "confidence": 0.0,
    "severity": null
  },
  {
    "line": 169,
    "token": 220,
    "index": 1,
    "confidence": 0.0,
    "severity": null
  },
  {
    "line": 169,
    "token": 220,
    "index": 2,
    "confidence": 0.0,
    "severity": null
  },
  {
    "line": 169,
    "token": 220,
    "index": 3,
    "confidence": 0.0,
    "severity": null
  },
  {
    "line": 169,
    "token": 220,
    "index": 4,
    "confidence": 0.0,
    "severity": null
  },
  {
    "line": 169,
    "token": 220,
    "index": 5,
    "confidence": 0.0,
    "severity": null
  },
  {
    "line": 169,
    "token": 220,
    "index": 6,
    "confidence": 0.0,
    "severity": null
  },
  {
    "line": 169,
    "token": 220,
    "index": 7,
    "confidence": 0.0,
    "severity": null
  },
  {
    "line": 169,
    "token": 220,
    "index": 8,
    "confidence": 0.0,
    "severity": null
  },
  {
    "line": 169,
    "token": 220,
    "index": 9,
    "confidence": 0.0,
    "severity": null
  },
  {
    "line": 169,
    "token": 220,
    "index": 10,
    "confidence": 0.0,
    "severity": null
  },
  {
    "line": 169,
    "token": 4283,
    "index": 11,
    "confidence": 0.0,
    "severity": null
  },
  {
    "line": 169,
    "token": 62,
    "index": 12,
    "confidence": 0.0,
    "severity": null
  },
  {
    "line": 169,
    "token": 312,
    "index": 13,
    "confidence": 0.0,
    "severity": null
  },
  {
    "line": 169,
    "token": 28,
    "index": 14,
    "confidence": 0.0,
    "severity": null
  },
  {
    "line": 169,
    "token": 808,
    "index": 15,
    "confidence": 0.0,
    "severity": null
  },
  {
    "line": 169,
    "token": 14692,
    "index": 16,
    "confidence": 0.0,
    "severity": null
  },
  {
    "line": 169,
    "token": 259,
    "index": 17,
    "confidence": 0.0,
    "severity": null
  },
  {
    "line": 169,
    "token": 43872,
    "index": 18,
    "confidence": 0.0,
    "severity": null
  },
  {
    "line": 169,
    "token": 33116,
    "index": 19,
    "confidence": 0.0,
    "severity": null
  },
  {
    "line": 177,
    "token": 220,
    "index": 0,
    "confidence": 0.0,
    "severity": null
  },
  {
    "line": 177,
    "token": 220,
    "index": 1,
    "confidence": 0.0,
    "severity": null
  },
  {
    "line": 177,
    "token": 220,
    "index": 2,
    "confidence": 0.0,
    "severity": null
  },
  {
    "line": 177,
    "token": 220,
    "index": 3,
    "confidence": 0.0,
    "severity": null
  },
  {
    "line": 177,
    "token": 220,
    "index": 4,
    "confidence": 0.0,
    "severity": null
  },
  {
    "line": 177,
    "token": 220,
    "index": 5,
    "confidence": 0.0,
    "severity": null
  },
  {
    "line": 177,
    "token": 220,
    "index": 6,
    "confidence": 0.0,
    "severity": null
  },
  {
    "line": 177,
    "token": 220,
    "index": 7,
    "confidence": 0.0,
    "severity": null
  },
  {
    "line": 177,
    "token": 220,
    "index": 8,
    "confidence": 0.0,
    "severity": null
  },
  {
    "line": 177,
    "token": 220,
    "index": 9,
    "confidence": 0.0,
    "severity": null
  },
  {
    "line": 177,
    "token": 220,
    "index": 10,
    "confidence": 0.0,
    "severity": null
  },
  {
    "line": 177,
    "token": 4811,
    "index": 11,
    "confidence": 0.0,
    "severity": null
  },
  {
    "line": 177,
    "token": 62,
    "index": 12,
    "confidence": 0.0,
    "severity": null
  },
  {
    "line": 177,
    "token": 11250,
    "index": 13,
    "confidence": 0.0,
    "severity": null
  },
  {
    "line": 177,
    "token": 28,
    "index": 14,
    "confidence": 0.0,
    "severity": null
  },
  {
    "line": 177,
    "token": 1891,
    "index": 15,
    "confidence": 0.0,
    "severity": null
  },
  {
    "line": 177,
    "token": 9288,
    "index": 16,
    "confidence": 0.0,
    "severity": null
  },
  {
    "line": 177,
    "token": 62,
    "index": 17,
    "confidence": 0.0,
    "severity": null
  },
  {
    "line": 177,
    "token": 11250,
    "index": 18,
    "confidence": 0.0,
    "severity": null
  },
  {
    "line": 177,
    "token": 14692,
    "index": 19,
    "confidence": 0.0,
    "severity": null
  },
  {
    "line": 177,
    "token": 2536,
    "index": 20,
    "confidence": 0.0,
    "severity": null
  },
  {
    "line": 177,
    "token": 2397,
    "index": 21,
    "confidence": 0.0,
    "severity": null
  },
  {
    "line": 177,
    "token": 444,
    "index": 22,
    "confidence": 0.0,
    "severity": null
  },
  {
    "line": 177,
    "token": 33116,
    "index": 23,
    "confidence": 0.0,
    "severity": null
  },
  {
    "line": 180,
    "token": 220,
    "index": 0,
    "confidence": 0.0,
    "severity": null
  },
  {
    "line": 180,
    "token": 220,
    "index": 1,
    "confidence": 0.0,
    "severity": null
  },
  {
    "line": 180,
    "token": 220,
    "index": 2,
    "confidence": 0.0,
    "severity": null
  },
  {
    "line": 180,
    "token": 220,
    "index": 3,
    "confidence": 0.0,
    "severity": null
  },
  {
    "line": 180,
    "token": 220,
    "index": 4,
    "confidence": 0.0,
    "severity": null
  },
  {
    "line": 180,
    "token": 220,
    "index": 5,
    "confidence": 0.0,
    "severity": null
  },
  {
    "line": 180,
    "token": 220,
    "index": 6,
    "confidence": 0.0,
    "severity": null
  },
  {
    "line": 180,
    "token": 220,
    "index": 7,
    "confidence": 0.0,
    "severity": null
  },
  {
    "line": 180,
    "token": 220,
    "index": 8,
    "confidence": 0.0,
    "severity": null
  },
  {
    "line": 180,
    "token": 220,
    "index": 9,
    "confidence": 0.0,
    "severity": null
  },
  {
    "line": 180,
    "token": 220,
    "index": 10,
    "confidence": 0.0,
    "severity": null
  },
  {
    "line": 180,
    "token": 1366,
    "index": 11,
    "confidence": 0.0,
    "severity": null
  },
  {
    "line": 180,
    "token": 62,
    "index": 12,
    "confidence": 0.0,
    "severity": null
  },
  {
    "line": 180,
    "token": 46324,
    "index": 13,
    "confidence": 0.0,
    "severity": null
  },
  {
    "line": 180,
    "token": 33737,
    "index": 14,
    "confidence": 0.0,
    "severity": null
  },
  {
    "line": 180,
    "token": 28,
    "index": 15,
    "confidence": 0.0,
    "severity": null
  },
  {
    "line": 180,
    "token": 1891,
    "index": 16,
    "confidence": 0.0,
    "severity": null
  },
  {
    "line": 180,
    "token": 9288,
    "index": 17,
    "confidence": 0.0,
    "severity": null
  },
  {
    "line": 180,
    "token": 62,
    "index": 18,
    "confidence": 0.0,
    "severity": null
  },
  {
    "line": 180,
    "token": 11250,
    "index": 19,
    "confidence": 0.0,
    "severity": null
  },
  {
    "line": 180,
    "token": 14692,
    "index": 20,
    "confidence": 0.0,
    "severity": null
  },
  {
    "line": 180,
    "token": 7890,
    "index": 21,
    "confidence": 0.0,
    "severity": null
  },
  {
    "line": 180,
    "token": 62,
    "index": 22,
    "confidence": 0.0,
    "severity": null
  },
  {
    "line": 180,
    "token": 46324,
    "index": 23,
    "confidence": 0.0,
    "severity": null
  },
  {
    "line": 180,
    "token": 33737,
    "index": 24,
    "confidence": 0.0,
    "severity": null
  },
  {
    "line": 180,
    "token": 33116,
    "index": 25,
    "confidence": 0.0,
    "severity": null
  },
  {
    "line": 181,
    "token": 220,
    "index": 0,
    "confidence": 0.0,
    "severity": null
  },
  {
    "line": 181,
    "token": 220,
    "index": 1,
    "confidence": 0.0,
    "severity": null
  },
  {
    "line": 181,
    "token": 220,
    "index": 2,
    "confidence": 0.0,
    "severity": null
  },
  {
    "line": 181,
    "token": 220,
    "index": 3,
    "confidence": 0.0,
    "severity": null
  },
  {
    "line": 181,
    "token": 220,
    "index": 4,
    "confidence": 0.0,
    "severity": null
  },
  {
    "line": 181,
    "token": 220,
    "index": 5,
    "confidence": 0.0,
    "severity": null
  },
  {
    "line": 181,
    "token": 220,
    "index": 6,
    "confidence": 0.0,
    "severity": null
  },
  {
    "line": 181,
    "token": 1267,
    "index": 7,
    "confidence": 0.0,
    "severity": null
  },
  {
    "line": 184,
    "token": 220,
    "index": 0,
    "confidence": 0.0,
    "severity": null
  },
  {
    "line": 184,
    "token": 220,
    "index": 1,
    "confidence": 0.0,
    "severity": null
  },
  {
    "line": 184,
    "token": 220,
    "index": 2,
    "confidence": 0.0,
    "severity": null
  },
  {
    "line": 184,
    "token": 220,
    "index": 3,
    "confidence": 0.0,
    "severity": null
  },
  {
    "line": 184,
    "token": 220,
    "index": 4,
    "confidence": 0.0,
    "severity": null
  },
  {
    "line": 184,
    "token": 220,
    "index": 5,
    "confidence": 0.0,
    "severity": null
  },
  {
    "line": 184,
    "token": 220,
    "index": 6,
    "confidence": 0.0,
    "severity": null
  },
  {
    "line": 184,
    "token": 5163,
    "index": 7,
    "confidence": 0.0,
    "severity": null
  },
  {
    "line": 184,
    "token": 62,
    "index": 8,
    "confidence": 0.0,
    "severity": null
  },
  {
    "line": 184,
    "token": 11250,
    "index": 9,
    "confidence": 0.0,
    "severity": null
  },
  {
    "line": 184,
    "token": 13,
    "index": 10,
    "confidence": 0.0,
    "severity": null
  },
  {
    "line": 184,
    "token": 19119,
    "index": 11,
    "confidence": 0.0,
    "severity": null
  },
  {
    "line": 184,
    "token": 7,
    "index": 12,
    "confidence": 0.0,
    "severity": null
  },
  {
    "line": 184,
    "token": 220,
    "index": 0,
    "confidence": 0.0,
    "severity": null
  },
  {
    "line": 184,
    "token": 220,
    "index": 1,
    "confidence": 0.0,
    "severity": null
  },
  {
    "line": 184,
    "token": 220,
    "index": 2,
    "confidence": 0.0,
    "severity": null
  },
  {
    "line": 184,
    "token": 220,
    "index": 3,
    "confidence": 0.0,
    "severity": null
  },
  {
    "line": 184,
    "token": 220,
    "index": 4,
    "confidence": 0.0,
    "severity": null
  },
  {
    "line": 184,
    "token": 220,
    "index": 5,
    "confidence": 0.0,
    "severity": null
  },
  {
    "line": 184,
    "token": 220,
    "index": 6,
    "confidence": 0.0,
    "severity": null
  },
  {
    "line": 184,
    "token": 5163,
    "index": 7,
    "confidence": 0.0,
    "severity": null
  },
  {
    "line": 184,
    "token": 62,
    "index": 8,
    "confidence": 0.0,
    "severity": null
  },
  {
    "line": 184,
    "token": 11250,
    "index": 9,
    "confidence": 0.0,
    "severity": null
  },
  {
    "line": 184,
    "token": 13,
    "index": 10,
    "confidence": 0.0,
    "severity": null
  },
  {
    "line": 184,
    "token": 19119,
    "index": 11,
    "confidence": 0.0,
    "severity": null
  },
  {
    "line": 184,
    "token": 7,
    "index": 12,
    "confidence": 0.0,
    "severity": null
  },
  {
    "line": 189,
    "token": 220,
    "index": 0,
    "confidence": 0.0,
    "severity": null
  },
  {
    "line": 189,
    "token": 220,
    "index": 1,
    "confidence": 0.0,
    "severity": null
  },
  {
    "line": 189,
    "token": 220,
    "index": 2,
    "confidence": 0.0,
    "severity": null
  },
  {
    "line": 189,
    "token": 220,
    "index": 3,
    "confidence": 0.0,
    "severity": null
  },
  {
    "line": 189,
    "token": 220,
    "index": 4,
    "confidence": 0.0,
    "severity": null
  },
  {
    "line": 189,
    "token": 220,
    "index": 5,
    "confidence": 0.0,
    "severity": null
  },
  {
    "line": 189,
    "token": 220,
    "index": 6,
    "confidence": 0.0,
    "severity": null
  },
  {
    "line": 189,
    "token": 1267,
    "index": 7,
    "confidence": 0.0,
    "severity": null
  },
  {
    "line": 191,
    "token": 220,
    "index": 0,
    "confidence": 0.0,
    "severity": null
  },
  {
    "line": 191,
    "token": 220,
    "index": 1,
    "confidence": 0.0,
    "severity": null
  },
  {
    "line": 191,
    "token": 220,
    "index": 2,
    "confidence": 0.0,
    "severity": null
  },
  {
    "line": 191,
    "token": 220,
    "index": 3,
    "confidence": 0.0,
    "severity": null
  },
  {
    "line": 191,
    "token": 220,
    "index": 4,
    "confidence": 0.0,
    "severity": null
  },
  {
    "line": 191,
    "token": 220,
    "index": 5,
    "confidence": 0.0,
    "severity": null
  },
  {
    "line": 191,
    "token": 220,
    "index": 6,
    "confidence": 0.0,
    "severity": null
  },
  {
    "line": 191,
    "token": 35375,
    "index": 7,
    "confidence": 0.0,
    "severity": null
  },
  {
    "line": 191,
    "token": 796,
    "index": 8,
    "confidence": 0.0,
    "severity": null
  },
  {
    "line": 191,
    "token": 14206,
    "index": 9,
    "confidence": 0.0,
    "severity": null
  },
  {
    "line": 191,
    "token": 45869,
    "index": 10,
    "confidence": 0.0,
    "severity": null
  },
  {
    "line": 191,
    "token": 18743,
    "index": 11,
    "confidence": 0.0,
    "severity": null
  },
  {
    "line": 191,
    "token": 23002,
    "index": 12,
    "confidence": 0.0,
    "severity": null
  },
  {
    "line": 191,
    "token": 1009,
    "index": 13,
    "confidence": 0.0,
    "severity": null
  },
  {
    "line": 191,
    "token": 7,
    "index": 14,
    "confidence": 0.0,
    "severity": null
  },
  {
    "line": 191,
    "token": 220,
    "index": 0,
    "confidence": 0.0,
    "severity": null
  },
  {
    "line": 191,
    "token": 220,
    "index": 1,
    "confidence": 0.0,
    "severity": null
  },
  {
    "line": 191,
    "token": 220,
    "index": 2,
    "confidence": 0.0,
    "severity": null
  },
  {
    "line": 191,
    "token": 220,
    "index": 3,
    "confidence": 0.0,
    "severity": null
  },
  {
    "line": 191,
    "token": 220,
    "index": 4,
    "confidence": 0.0,
    "severity": null
  },
  {
    "line": 191,
    "token": 220,
    "index": 5,
    "confidence": 0.0,
    "severity": null
  },
  {
    "line": 191,
    "token": 220,
    "index": 6,
    "confidence": 0.0,
    "severity": null
  },
  {
    "line": 191,
    "token": 35375,
    "index": 7,
    "confidence": 0.0,
    "severity": null
  },
  {
    "line": 191,
    "token": 796,
    "index": 8,
    "confidence": 0.0,
    "severity": null
  },
  {
    "line": 191,
    "token": 14206,
    "index": 9,
    "confidence": 0.0,
    "severity": null
  },
  {
    "line": 191,
    "token": 45869,
    "index": 10,
    "confidence": 0.0,
    "severity": null
  },
  {
    "line": 191,
    "token": 18743,
    "index": 11,
    "confidence": 0.0,
    "severity": null
  },
  {
    "line": 191,
    "token": 23002,
    "index": 12,
    "confidence": 0.0,
    "severity": null
  },
  {
    "line": 191,
    "token": 1009,
    "index": 13,
    "confidence": 0.0,
    "severity": null
  },
  {
    "line": 191,
    "token": 7,
    "index": 14,
    "confidence": 0.0,
    "severity": null
  },
  {
    "line": 212,
    "token": 220,
    "index": 0,
    "confidence": 0.0,
    "severity": null
  },
  {
    "line": 212,
    "token": 220,
    "index": 1,
    "confidence": 0.0,
    "severity": null
  },
  {
    "line": 212,
    "token": 220,
    "index": 2,
    "confidence": 0.0,
    "severity": null
  },
  {
    "line": 212,
    "token": 220,
    "index": 3,
    "confidence": 0.0,
    "severity": null
  },
  {
    "line": 212,
    "token": 220,
    "index": 4,
    "confidence": 0.0,
    "severity": null
  },
  {
    "line": 212,
    "token": 220,
    "index": 5,
    "confidence": 0.0,
    "severity": null
  },
  {
    "line": 212,
    "token": 220,
    "index": 6,
    "confidence": 0.0,
    "severity": null
  },
  {
    "line": 212,
    "token": 220,
    "index": 7,
    "confidence": 0.0,
    "severity": null
  },
  {
    "line": 212,
    "token": 220,
    "index": 8,
    "confidence": 0.0,
    "severity": null
  },
  {
    "line": 212,
    "token": 220,
    "index": 9,
    "confidence": 0.0,
    "severity": null
  },
  {
    "line": 212,
    "token": 220,
    "index": 10,
    "confidence": 0.0,
    "severity": null
  },
  {
    "line": 212,
    "token": 989,
    "index": 11,
    "confidence": 0.0,
    "severity": null
  },
  {
    "line": 212,
    "token": 796,
    "index": 12,
    "confidence": 0.0,
    "severity": null
  },
  {
    "line": 212,
    "token": 1391,
    "index": 13,
    "confidence": 0.0,
    "severity": null
  },
  {
    "line": 212,
    "token": 13578,
    "index": 14,
    "confidence": 0.0,
    "severity": null
  },
  {
    "line": 212,
    "token": 62,
    "index": 15,
    "confidence": 0.0,
    "severity": null
  },
  {
    "line": 212,
    "token": 312,
    "index": 16,
    "confidence": 0.0,
    "severity": null
  },
  {
    "line": 212,
    "token": 25,
    "index": 17,
    "confidence": 0.0,
    "severity": null
  },
  {
    "line": 212,
    "token": 4808,
    "index": 18,
    "confidence": 0.0,
    "severity": null
  },
  {
    "line": 212,
    "token": 13116,
    "index": 19,
    "confidence": 0.0,
    "severity": null
  },
  {
    "line": 212,
    "token": 92,
    "index": 20,
    "confidence": 0.0,
    "severity": null
  },
  {
    "line": 214,
    "token": 220,
    "index": 0,
    "confidence": 0.0,
    "severity": null
  },
  {
    "line": 214,
    "token": 220,
    "index": 1,
    "confidence": 0.0,
    "severity": null
  },
  {
    "line": 214,
    "token": 220,
    "index": 2,
    "confidence": 0.0,
    "severity": null
  },
  {
    "line": 214,
    "token": 220,
    "index": 3,
    "confidence": 0.0,
    "severity": null
  },
  {
    "line": 214,
    "token": 220,
    "index": 4,
    "confidence": 0.0,
    "severity": null
  },
  {
    "line": 214,
    "token": 220,
    "index": 5,
    "confidence": 0.0,
    "severity": null
  },
  {
    "line": 214,
    "token": 220,
    "index": 6,
    "confidence": 0.0,
    "severity": null
  },
  {
    "line": 214,
    "token": 220,
    "index": 7,
    "confidence": 0.0,
    "severity": null
  },
  {
    "line": 214,
    "token": 220,
    "index": 8,
    "confidence": 0.0,
    "severity": null
  },
  {
    "line": 214,
    "token": 220,
    "index": 9,
    "confidence": 0.0,
    "severity": null
  },
  {
    "line": 214,
    "token": 220,
    "index": 10,
    "confidence": 0.0,
    "severity": null
  },
  {
    "line": 214,
    "token": 1110,
    "index": 11,
    "confidence": 0.0,
    "severity": null
  },
  {
    "line": 214,
    "token": 796,
    "index": 12,
    "confidence": 0.0,
    "severity": null
  },
  {
    "line": 214,
    "token": 6266,
    "index": 13,
    "confidence": 0.0,
    "severity": null
  },
  {
    "line": 214,
    "token": 13,
    "index": 14,
    "confidence": 0.0,
    "severity": null
  },
  {
    "line": 214,
    "token": 346,
    "index": 15,
    "confidence": 0.0,
    "severity": null
  },
  {
    "line": 214,
    "token": 420,
    "index": 16,
    "confidence": 0.0,
    "severity": null
  },
  {
    "line": 214,
    "token": 58,
    "index": 17,
    "confidence": 0.0,
    "severity": null
  },
  {
    "line": 214,
    "token": 15,
    "index": 18,
    "confidence": 0.0,
    "severity": null
  },
  {
    "line": 214,
    "token": 4083,
    "index": 19,
    "confidence": 0.0,
    "severity": null
  },
  {
    "line": 214,
    "token": 19608,
    "index": 20,
    "confidence": 0.0,
    "severity": null
  },
  {
    "line": 214,
    "token": 8079,
    "index": 21,
    "confidence": 0.0,
    "severity": null
  },
  {
    "line": 234,
    "token": 220,
    "index": 0,
    "confidence": 0.0,
    "severity": null
  },
  {
    "line": 234,
    "token": 220,
    "index": 1,
    "confidence": 0.0,
    "severity": null
  },
  {
    "line": 234,
    "token": 220,
    "index": 2,
    "confidence": 0.0,
    "severity": null
  },
  {
    "line": 234,
    "token": 220,
    "index": 3,
    "confidence": 0.0,
    "severity": null
  },
  {
    "line": 234,
    "token": 220,
    "index": 4,
    "confidence": 0.0,
    "severity": null
  },
  {
    "line": 234,
    "token": 220,
    "index": 5,
    "confidence": 0.0,
    "severity": null
  },
  {
    "line": 234,
    "token": 220,
    "index": 6,
    "confidence": 0.0,
    "severity": null
  },
  {
    "line": 234,
    "token": 5157,
    "index": 7,
    "confidence": 0.0,
    "severity": null
  },
  {
    "line": 234,
    "token": 9288,
    "index": 8,
    "confidence": 0.0,
    "severity": null
  },
  {
    "line": 234,
    "token": 4566,
    "index": 9,
    "confidence": 0.0,
    "severity": null
  },
  {
    "line": 255,
    "token": 220,
    "index": 0,
    "confidence": 0.0,
    "severity": null
  },
  {
    "line": 255,
    "token": 220,
    "index": 1,
    "confidence": 0.0,
    "severity": null
  },
  {
    "line": 255,
    "token": 220,
    "index": 2,
    "confidence": 0.0,
    "severity": null
  },
  {
    "line": 255,
    "token": 3292,
    "index": 3,
    "confidence": 0.0,
    "severity": null
  },
  {
    "line": 255,
    "token": 62,
    "index": 4,
    "confidence": 0.0,
    "severity": null
  },
  {
    "line": 255,
    "token": 9688,
    "index": 5,
    "confidence": 0.0,
    "severity": null
  },
  {
    "line": 255,
    "token": 62,
    "index": 6,
    "confidence": 0.0,
    "severity": null
  },
  {
    "line": 255,
    "token": 2435,
    "index": 7,
    "confidence": 0.0,
    "severity": null
  },
  {
    "line": 255,
    "token": 796,
    "index": 8,
    "confidence": 0.0,
    "severity": null
  },
  {
    "line": 255,
    "token": 6266,
    "index": 9,
    "confidence": 0.0,
    "severity": null
  },
  {
    "line": 255,
    "token": 14692,
    "index": 10,
    "confidence": 0.0,
    "severity": null
  },
  {
    "line": 255,
    "token": 19608,
    "index": 11,
    "confidence": 0.0,
    "severity": null
  },
  {
    "line": 255,
    "token": 8079,
    "index": 12,
    "confidence": 0.0,
    "severity": null
  },
  {
    "line": 255,
    "token": 1,
    "index": 13,
    "confidence": 0.0,
    "severity": null
  },
  {
    "line": 255,
    "token": 4083,
    "index": 14,
    "confidence": 0.0,
    "severity": null
  },
  {
    "line": 255,
    "token": 1084,
    "index": 15,
    "confidence": 0.0,
    "severity": null
  },
  {
    "line": 255,
    "token": 3419,
    "index": 16,
    "confidence": 0.0,
    "severity": null
  },
  {
    "line": 259,
    "token": 220,
    "index": 0,
    "confidence": 0.0,
    "severity": null
  },
  {
    "line": 259,
    "token": 220,
    "index": 1,
    "confidence": 0.0,
    "severity": null
  },
  {
    "line": 259,
    "token": 220,
    "index": 2,
    "confidence": 0.0,
    "severity": null
  },
  {
    "line": 259,
    "token": 4811,
    "index": 3,
    "confidence": 0.0,
    "severity": null
  },
  {
    "line": 259,
    "token": 62,
    "index": 4,
    "confidence": 0.0,
    "severity": null
  },
  {
    "line": 259,
    "token": 11250,
    "index": 5,
    "confidence": 0.0,
    "severity": null
  },
  {
    "line": 259,
    "token": 796,
    "index": 6,
    "confidence": 0.0,
    "severity": null
  },
  {
    "line": 259,
    "token": 1391,
    "index": 7,
    "confidence": 0.0,
    "severity": null
  },
  {
    "line": 263,
    "token": 220,
    "index": 0,
    "confidence": 0.0,
    "severity": null
  },
  {
    "line": 263,
    "token": 220,
    "index": 1,
    "confidence": 0.0,
    "severity": null
  },
  {
    "line": 263,
    "token": 220,
    "index": 2,
    "confidence": 0.0,
    "severity": null
  },
  {
    "line": 263,
    "token": 220,
    "index": 3,
    "confidence": 0.0,
    "severity": null
  },
  {
    "line": 263,
    "token": 220,
    "index": 4,
    "confidence": 0.0,
    "severity": null
  },
  {
    "line": 263,
    "token": 220,
    "index": 5,
    "confidence": 0.0,
    "severity": null
  },
  {
    "line": 263,
    "token": 220,
    "index": 6,
    "confidence": 0.0,
    "severity": null
  },
  {
    "line": 263,
    "token": 220,
    "index": 7,
    "confidence": 0.0,
    "severity": null
  },
  {
    "line": 263,
    "token": 220,
    "index": 8,
    "confidence": 0.0,
    "severity": null
  },
  {
    "line": 263,
    "token": 220,
    "index": 9,
    "confidence": 0.0,
    "severity": null
  },
  {
    "line": 263,
    "token": 220,
    "index": 10,
    "confidence": 0.0,
    "severity": null
  },
  {
    "line": 263,
    "token": 366,
    "index": 11,
    "confidence": 0.0,
    "severity": null
  },
  {
    "line": 263,
    "token": 7753,
    "index": 12,
    "confidence": 0.0,
    "severity": null
  },
  {
    "line": 263,
    "token": 1298,
    "index": 13,
    "confidence": 0.0,
    "severity": null
  },
  {
    "line": 263,
    "token": 6266,
    "index": 14,
    "confidence": 0.0,
    "severity": null
  },
  {
    "line": 263,
    "token": 11,
    "index": 15,
    "confidence": 0.0,
    "severity": null
  },
  {
    "line": 268,
    "token": 220,
    "index": 0,
    "confidence": 0.0,
    "severity": null
  },
  {
    "line": 268,
    "token": 220,
    "index": 1,
    "confidence": 0.0,
    "severity": null
  },
  {
    "line": 268,
    "token": 220,
    "index": 2,
    "confidence": 0.0,
    "severity": null
  },
  {
    "line": 268,
    "token": 220,
    "index": 3,
    "confidence": 0.0,
    "severity": null
  },
  {
    "line": 268,
    "token": 220,
    "index": 4,
    "confidence": 0.0,
    "severity": null
  },
  {
    "line": 268,
    "token": 220,
    "index": 5,
    "confidence": 0.0,
    "severity": null
  },
  {
    "line": 268,
    "token": 220,
    "index": 6,
    "confidence": 0.0,
    "severity": null
  },
  {
    "line": 268,
    "token": 8964,
    "index": 7,
    "confidence": 0.0,
    "severity": null
  },
  {
    "line": 267,
    "token": 220,
    "index": 0,
    "confidence": 0.0,
    "severity": null
  },
  {
    "line": 267,
    "token": 220,
    "index": 1,
    "confidence": 0.0,
    "severity": null
  },
  {
    "line": 267,
    "token": 220,
    "index": 2,
    "confidence": 0.0,
    "severity": null
  },
  {
    "line": 267,
    "token": 220,
    "index": 3,
    "confidence": 0.0,
    "severity": null
  },
  {
    "line": 267,
    "token": 220,
    "index": 4,
    "confidence": 0.0,
    "severity": null
  },
  {
    "line": 267,
    "token": 220,
    "index": 5,
    "confidence": 0.0,
    "severity": null
  },
  {
    "line": 267,
    "token": 220,
    "index": 6,
    "confidence": 0.0,
    "severity": null
  },
  {
    "line": 267,
    "token": 220,
    "index": 7,
    "confidence": 0.0,
    "severity": null
  },
  {
    "line": 267,
    "token": 220,
    "index": 8,
    "confidence": 0.0,
    "severity": null
  },
  {
    "line": 267,
    "token": 220,
    "index": 9,
    "confidence": 0.0,
    "severity": null
  },
  {
    "line": 267,
    "token": 220,
    "index": 10,
    "confidence": 0.0,
    "severity": null
  },
  {
    "line": 267,
    "token": 10612,
    "index": 11,
    "confidence": 0.0,
    "severity": null
  },
  {
    "line": 269,
    "token": 220,
    "index": 0,
    "confidence": 0.0,
    "severity": null
  },
  {
    "line": 269,
    "token": 220,
    "index": 1,
    "confidence": 0.0,
    "severity": null
  },
  {
    "line": 269,
    "token": 220,
    "index": 2,
    "confidence": 0.0,
    "severity": null
  },
  {
    "line": 269,
    "token": 1782,
    "index": 3,
    "confidence": 0.0,
    "severity": null
  },
  {
    "line": 271,
    "token": 220,
    "index": 0,
    "confidence": 0.0,
    "severity": null
  },
  {
    "line": 271,
    "token": 220,
    "index": 1,
    "confidence": 0.0,
    "severity": null
  },
  {
    "line": 271,
    "token": 220,
    "index": 2,
    "confidence": 0.0,
    "severity": null
  },
  {
    "line": 271,
    "token": 3121,
    "index": 3,
    "confidence": 0.0,
    "severity": null
  },
  {
    "line": 271,
    "token": 273,
    "index": 4,
    "confidence": 0.0,
    "severity": null
  },
  {
    "line": 271,
    "token": 62,
    "index": 5,
    "confidence": 0.0,
    "severity": null
  },
  {
    "line": 271,
    "token": 11250,
    "index": 6,
    "confidence": 0.0,
    "severity": null
  },
  {
    "line": 271,
    "token": 796,
    "index": 7,
    "confidence": 0.0,
    "severity": null
  },
  {
    "line": 271,
    "token": 4808,
    "index": 8,
    "confidence": 0.0,
    "severity": null
  },
  {
    "line": 271,
    "token": 1136,
    "index": 9,
    "confidence": 0.0,
    "severity": null
  },
  {
    "line": 271,
    "token": 62,
    "index": 10,
    "confidence": 0.0,
    "severity": null
  },
  {
    "line": 271,
    "token": 41684,
    "index": 11,
    "confidence": 0.0,
    "severity": null
  },
  {
    "line": 271,
    "token": 62,
    "index": 12,
    "confidence": 0.0,
    "severity": null
  },
  {
    "line": 271,
    "token": 5715,
    "index": 13,
    "confidence": 0.0,
    "severity": null
  },
  {
    "line": 271,
    "token": 62,
    "index": 14,
    "confidence": 0.0,
    "severity": null
  },
  {
    "line": 271,
    "token": 18558,
    "index": 15,
    "confidence": 0.0,
    "severity": null
  },
  {
    "line": 271,
    "token": 38409,
    "index": 16,
    "confidence": 0.0,
    "severity": null
  },
  {
    "line": 271,
    "token": 62,
    "index": 17,
    "confidence": 0.0,
    "severity": null
  },
  {
    "line": 271,
    "token": 11250,
    "index": 18,
    "confidence": 0.0,
    "severity": null
  },
  {
    "line": 271,
    "token": 7,
    "index": 19,
    "confidence": 0.0,
    "severity": null
  },
  {
    "line": 275,
    "token": 220,
    "index": 0,
    "confidence": 0.0,
    "severity": null
  },
  {
    "line": 275,
    "token": 220,
    "index": 1,
    "confidence": 0.0,
    "severity": null
  },
  {
    "line": 275,
    "token": 220,
    "index": 2,
    "confidence": 0.0,
    "severity": null
  },
  {
    "line": 275,
    "token": 220,
    "index": 3,
    "confidence": 0.0,
    "severity": null
  },
  {
    "line": 275,
    "token": 220,
    "index": 4,
    "confidence": 0.0,
    "severity": null
  },
  {
    "line": 275,
    "token": 220,
    "index": 5,
    "confidence": 0.0,
    "severity": null
  },
  {
    "line": 275,
    "token": 220,
    "index": 6,
    "confidence": 0.0,
    "severity": null
  },
  {
    "line": 275,
    "token": 1366,
    "index": 7,
    "confidence": 0.0,
    "severity": null
  },
  {
    "line": 275,
    "token": 62,
    "index": 8,
    "confidence": 0.0,
    "severity": null
  },
  {
    "line": 275,
    "token": 46324,
    "index": 9,
    "confidence": 0.0,
    "severity": null
  },
  {
    "line": 275,
    "token": 33737,
    "index": 10,
    "confidence": 0.0,
    "severity": null
  },
  {
    "line": 275,
    "token": 28,
    "index": 11,
    "confidence": 0.0,
    "severity": null
  },
  {
    "line": 275,
    "token": 1891,
    "index": 12,
    "confidence": 0.0,
    "severity": null
  },
  {
    "line": 275,
    "token": 9288,
    "index": 13,
    "confidence": 0.0,
    "severity": null
  },
  {
    "line": 275,
    "token": 62,
    "index": 14,
    "confidence": 0.0,
    "severity": null
  },
  {
    "line": 275,
    "token": 11250,
    "index": 15,
    "confidence": 0.0,
    "severity": null
  },
  {
    "line": 275,
    "token": 14692,
    "index": 16,
    "confidence": 0.0,
    "severity": null
  },
  {
    "line": 275,
    "token": 7890,
    "index": 17,
    "confidence": 0.0,
    "severity": null
  },
  {
    "line": 275,
    "token": 62,
    "index": 18,
    "confidence": 0.0,
    "severity": null
  },
  {
    "line": 275,
    "token": 46324,
    "index": 19,
    "confidence": 0.0,
    "severity": null
  },
  {
    "line": 275,
    "token": 33737,
    "index": 20,
    "confidence": 0.0,
    "severity": null
  },
  {
    "line": 275,
    "token": 33116,
    "index": 21,
    "confidence": 0.0,
    "severity": null
  },
  {
    "line": 275,
    "token": 220,
    "index": 0,
    "confidence": 0.0,
    "severity": null
  },
  {
    "line": 275,
    "token": 220,
    "index": 1,
    "confidence": 0.0,
    "severity": null
  },
  {
    "line": 275,
    "token": 220,
    "index": 2,
    "confidence": 0.0,
    "severity": null
  },
  {
    "line": 275,
    "token": 220,
    "index": 3,
    "confidence": 0.0,
    "severity": null
  },
  {
    "line": 275,
    "token": 220,
    "index": 4,
    "confidence": 0.0,
    "severity": null
  },
  {
    "line": 275,
    "token": 220,
    "index": 5,
    "confidence": 0.0,
    "severity": null
  },
  {
    "line": 275,
    "token": 220,
    "index": 6,
    "confidence": 0.0,
    "severity": null
  },
  {
    "line": 275,
    "token": 1366,
    "index": 7,
    "confidence": 0.0,
    "severity": null
  },
  {
    "line": 275,
    "token": 62,
    "index": 8,
    "confidence": 0.0,
    "severity": null
  },
  {
    "line": 275,
    "token": 46324,
    "index": 9,
    "confidence": 0.0,
    "severity": null
  },
  {
    "line": 275,
    "token": 33737,
    "index": 10,
    "confidence": 0.0,
    "severity": null
  },
  {
    "line": 275,
    "token": 28,
    "index": 11,
    "confidence": 0.0,
    "severity": null
  },
  {
    "line": 275,
    "token": 1891,
    "index": 12,
    "confidence": 0.0,
    "severity": null
  },
  {
    "line": 275,
    "token": 9288,
    "index": 13,
    "confidence": 0.0,
    "severity": null
  },
  {
    "line": 275,
    "token": 62,
    "index": 14,
    "confidence": 0.0,
    "severity": null
  },
  {
    "line": 275,
    "token": 11250,
    "index": 15,
    "confidence": 0.0,
    "severity": null
  },
  {
    "line": 275,
    "token": 14692,
    "index": 16,
    "confidence": 0.0,
    "severity": null
  },
  {
    "line": 275,
    "token": 7890,
    "index": 17,
    "confidence": 0.0,
    "severity": null
  },
  {
    "line": 275,
    "token": 62,
    "index": 18,
    "confidence": 0.0,
    "severity": null
  },
  {
    "line": 275,
    "token": 46324,
    "index": 19,
    "confidence": 0.0,
    "severity": null
  },
  {
    "line": 275,
    "token": 33737,
    "index": 20,
    "confidence": 0.0,
    "severity": null
  },
  {
    "line": 275,
    "token": 33116,
    "index": 21,
    "confidence": 0.0,
    "severity": null
  },
  {
    "line": 275,
    "token": 220,
    "index": 0,
    "confidence": 0.0,
    "severity": null
  },
  {
    "line": 275,
    "token": 220,
    "index": 1,
    "confidence": 0.0,
    "severity": null
  },
  {
    "line": 275,
    "token": 220,
    "index": 2,
    "confidence": 0.0,
    "severity": null
  },
  {
    "line": 275,
    "token": 220,
    "index": 3,
    "confidence": 0.0,
    "severity": null
  },
  {
    "line": 275,
    "token": 220,
    "index": 4,
    "confidence": 0.0,
    "severity": null
  },
  {
    "line": 275,
    "token": 220,
    "index": 5,
    "confidence": 0.0,
    "severity": null
  },
  {
    "line": 275,
    "token": 220,
    "index": 6,
    "confidence": 0.0,
    "severity": null
  },
  {
    "line": 275,
    "token": 1366,
    "index": 7,
    "confidence": 0.0,
    "severity": null
  },
  {
    "line": 275,
    "token": 62,
    "index": 8,
    "confidence": 0.0,
    "severity": null
  },
  {
    "line": 275,
    "token": 46324,
    "index": 9,
    "confidence": 0.0,
    "severity": null
  },
  {
    "line": 275,
    "token": 33737,
    "index": 10,
    "confidence": 0.0,
    "severity": null
  },
  {
    "line": 275,
    "token": 28,
    "index": 11,
    "confidence": 0.0,
    "severity": null
  },
  {
    "line": 275,
    "token": 1891,
    "index": 12,
    "confidence": 0.0,
    "severity": null
  },
  {
    "line": 275,
    "token": 9288,
    "index": 13,
    "confidence": 0.0,
    "severity": null
  },
  {
    "line": 275,
    "token": 62,
    "index": 14,
    "confidence": 0.0,
    "severity": null
  },
  {
    "line": 275,
    "token": 11250,
    "index": 15,
    "confidence": 0.0,
    "severity": null
  },
  {
    "line": 275,
    "token": 14692,
    "index": 16,
    "confidence": 0.0,
    "severity": null
  },
  {
    "line": 275,
    "token": 7890,
    "index": 17,
    "confidence": 0.0,
    "severity": null
  },
  {
    "line": 275,
    "token": 62,
    "index": 18,
    "confidence": 0.0,
    "severity": null
  },
  {
    "line": 275,
    "token": 46324,
    "index": 19,
    "confidence": 0.0,
    "severity": null
  },
  {
    "line": 275,
    "token": 33737,
    "index": 20,
    "confidence": 0.0,
    "severity": null
  },
  {
    "line": 275,
    "token": 33116,
    "index": 21,
    "confidence": 0.0,
    "severity": null
  },
  {
    "line": 291,
    "token": 220,
    "index": 0,
    "confidence": 0.0,
    "severity": null
  },
  {
    "line": 291,
    "token": 220,
    "index": 1,
    "confidence": 0.0,
    "severity": null
  },
  {
    "line": 291,
    "token": 220,
    "index": 2,
    "confidence": 0.0,
    "severity": null
  },
  {
    "line": 291,
    "token": 220,
    "index": 3,
    "confidence": 0.0,
    "severity": null
  },
  {
    "line": 291,
    "token": 220,
    "index": 4,
    "confidence": 0.0,
    "severity": null
  },
  {
    "line": 291,
    "token": 220,
    "index": 5,
    "confidence": 0.0,
    "severity": null
  },
  {
    "line": 291,
    "token": 220,
    "index": 6,
    "confidence": 0.0,
    "severity": null
  },
  {
    "line": 291,
    "token": 18335,
    "index": 7,
    "confidence": 0.0,
    "severity": null
  },
  {
    "line": 291,
    "token": 28,
    "index": 8,
    "confidence": 0.0,
    "severity": null
  },
  {
    "line": 291,
    "token": 14202,
    "index": 9,
    "confidence": 0.0,
    "severity": null
  },
  {
    "line": 291,
    "token": 11,
    "index": 10,
    "confidence": 0.0,
    "severity": null
  },
  {
    "line": 298,
    "token": 220,
    "index": 0,
    "confidence": 0.0,
    "severity": null
  },
  {
    "line": 298,
    "token": 220,
    "index": 1,
    "confidence": 0.0,
    "severity": null
  },
  {
    "line": 298,
    "token": 220,
    "index": 2,
    "confidence": 0.0,
    "severity": null
  },
  {
    "line": 298,
    "token": 5370,
    "index": 3,
    "confidence": 0.0,
    "severity": null
  },
  {
    "line": 298,
    "token": 796,
    "index": 4,
    "confidence": 0.0,
    "severity": null
  },
  {
    "line": 298,
    "token": 1351,
    "index": 5,
    "confidence": 0.0,
    "severity": null
  },
  {
    "line": 298,
    "token": 7,
    "index": 6,
    "confidence": 0.0,
    "severity": null
  },
  {
    "line": 298,
    "token": 33327,
    "index": 7,
    "confidence": 0.0,
    "severity": null
  },
  {
    "line": 298,
    "token": 62,
    "index": 8,
    "confidence": 0.0,
    "severity": null
  },
  {
    "line": 298,
    "token": 7890,
    "index": 9,
    "confidence": 0.0,
    "severity": null
  },
  {
    "line": 298,
    "token": 62,
    "index": 10,
    "confidence": 0.0,
    "severity": null
  },
  {
    "line": 298,
    "token": 26268,
    "index": 11,
    "confidence": 0.0,
    "severity": null
  },
  {
    "line": 298,
    "token": 7,
    "index": 12,
    "confidence": 0.0,
    "severity": null
  },
  {
    "line": 298,
    "token": 25351,
    "index": 13,
    "confidence": 0.0,
    "severity": null
  },
  {
    "line": 298,
    "token": 62,
    "index": 14,
    "confidence": 0.0,
    "severity": null
  },
  {
    "line": 298,
    "token": 9688,
    "index": 15,
    "confidence": 0.0,
    "severity": null
  },
  {
    "line": 298,
    "token": 62,
    "index": 16,
    "confidence": 0.0,
    "severity": null
  },
  {
    "line": 298,
    "token": 2435,
    "index": 17,
    "confidence": 0.0,
    "severity": null
  },
  {
    "line": 298,
    "token": 11,
    "index": 18,
    "confidence": 0.0,
    "severity": null
  },
  {
    "line": 298,
    "token": 3292,
    "index": 19,
    "confidence": 0.0,
    "severity": null
  },
  {
    "line": 298,
    "token": 62,
    "index": 20,
    "confidence": 0.0,
    "severity": null
  },
  {
    "line": 298,
    "token": 437,
    "index": 21,
    "confidence": 0.0,
    "severity": null
  },
  {
    "line": 298,
    "token": 62,
    "index": 22,
    "confidence": 0.0,
    "severity": null
  },
  {
    "line": 298,
    "token": 2435,
    "index": 23,
    "confidence": 0.0,
    "severity": null
  },
  {
    "line": 298,
    "token": 11,
    "index": 24,
    "confidence": 0.0,
    "severity": null
  },
  {
    "line": 298,
    "token": 4811,
    "index": 25,
    "confidence": 0.0,
    "severity": null
  },
  {
    "line": 298,
    "token": 11,
    "index": 26,
    "confidence": 0.0,
    "severity": null
  },
  {
    "line": 298,
    "token": 3121,
    "index": 27,
    "confidence": 0.0,
    "severity": null
  },
  {
    "line": 298,
    "token": 273,
    "index": 28,
    "confidence": 0.0,
    "severity": null
  },
  {
    "line": 298,
    "token": 11,
    "index": 29,
    "confidence": 0.0,
    "severity": null
  },
  {
    "line": 298,
    "token": 989,
    "index": 30,
    "confidence": 0.0,
    "severity": null
  },
  {
    "line": 298,
    "token": 62,
    "index": 31,
    "confidence": 0.0,
    "severity": null
  },
  {
    "line": 298,
    "token": 11600,
    "index": 32,
    "confidence": 0.0,
    "severity": null
  },
  {
    "line": 298,
    "token": 4008,
    "index": 33,
    "confidence": 0.0,
    "severity": null
  },
  {
    "line": 300,
    "token": 220,
    "index": 0,
    "confidence": 0.0,
    "severity": null
  },
  {
    "line": 300,
    "token": 220,
    "index": 1,
    "confidence": 0.0,
    "severity": null
  },
  {
    "line": 300,
    "token": 220,
    "index": 2,
    "confidence": 0.0,
    "severity": null
  },
  {
    "line": 300,
    "token": 16916,
    "index": 3,
    "confidence": 0.0,
    "severity": null
  },
  {
    "line": 300,
    "token": 62,
    "index": 4,
    "confidence": 0.0,
    "severity": null
  },
  {
    "line": 300,
    "token": 11600,
    "index": 5,
    "confidence": 0.0,
    "severity": null
  },
  {
    "line": 300,
    "token": 796,
    "index": 6,
    "confidence": 0.0,
    "severity": null
  },
  {
    "line": 300,
    "token": 3350,
    "index": 7,
    "confidence": 0.0,
    "severity": null
  },
  {
    "line": 300,
    "token": 7,
    "index": 8,
    "confidence": 0.0,
    "severity": null
  },
  {
    "line": 300,
    "token": 12115,
    "index": 9,
    "confidence": 0.0,
    "severity": null
  },
  {
    "line": 300,
    "token": 2149,
    "index": 10,
    "confidence": 0.0,
    "severity": null
  },
  {
    "line": 300,
    "token": 25633,
    "index": 11,
    "confidence": 0.0,
    "severity": null
  },
  {
    "line": 300,
    "token": 62,
    "index": 12,
    "confidence": 0.0,
    "severity": null
  },
  {
    "line": 300,
    "token": 47123,
    "index": 13,
    "confidence": 0.0,
    "severity": null
  },
  {
    "line": 300,
    "token": 41132,
    "index": 14,
    "confidence": 0.0,
    "severity": null
  },
  {
    "line": 300,
    "token": 11,
    "index": 15,
    "confidence": 0.0,
    "severity": null
  },
  {
    "line": 300,
    "token": 989,
    "index": 16,
    "confidence": 0.0,
    "severity": null
  },
  {
    "line": 300,
    "token": 62,
    "index": 17,
    "confidence": 0.0,
    "severity": null
  },
  {
    "line": 300,
    "token": 11600,
    "index": 18,
    "confidence": 0.0,
    "severity": null
  },
  {
    "line": 300,
    "token": 13,
    "index": 19,
    "confidence": 0.0,
    "severity": null
  },
  {
    "line": 300,
    "token": 1136,
    "index": 20,
    "confidence": 0.0,
    "severity": null
  },
  {
    "line": 300,
    "token": 7203,
    "index": 21,
    "confidence": 0.0,
    "severity": null
  },
  {
    "line": 300,
    "token": 521,
    "index": 22,
    "confidence": 0.0,
    "severity": null
  },
  {
    "line": 300,
    "token": 26407,
    "index": 23,
    "confidence": 0.0,
    "severity": null
  },
  {
    "line": 300,
    "token": 62,
    "index": 24,
    "confidence": 0.0,
    "severity": null
  },
  {
    "line": 300,
    "token": 11600,
    "index": 25,
    "confidence": 0.0,
    "severity": null
  },
  {
    "line": 300,
    "token": 48774,
    "index": 26,
    "confidence": 0.0,
    "severity": null
  },
  {
    "line": 304,
    "token": 220,
    "index": 0,
    "confidence": 0.0,
    "severity": null
  },
  {
    "line": 304,
    "token": 220,
    "index": 1,
    "confidence": 0.0,
    "severity": null
  },
  {
    "line": 304,
    "token": 220,
    "index": 2,
    "confidence": 0.0,
    "severity": null
  },
  {
    "line": 304,
    "token": 611,
    "index": 3,
    "confidence": 0.0,
    "severity": null
  },
  {
    "line": 304,
    "token": 7716,
    "index": 4,
    "confidence": 0.0,
    "severity": null
  },
  {
    "line": 304,
    "token": 62,
    "index": 5,
    "confidence": 0.0,
    "severity": null
  },
  {
    "line": 304,
    "token": 13116,
    "index": 6,
    "confidence": 0.0,
    "severity": null
  },
  {
    "line": 304,
    "token": 25,
    "index": 7,
    "confidence": 0.0,
    "severity": null
  },
  {
    "line": 314,
    "token": 220,
    "index": 0,
    "confidence": 0.0,
    "severity": null
  },
  {
    "line": 314,
    "token": 220,
    "index": 1,
    "confidence": 0.0,
    "severity": null
  },
  {
    "line": 314,
    "token": 220,
    "index": 2,
    "confidence": 0.0,
    "severity": null
  },
  {
    "line": 314,
    "token": 220,
    "index": 3,
    "confidence": 0.0,
    "severity": null
  },
  {
    "line": 314,
    "token": 220,
    "index": 4,
    "confidence": 0.0,
    "severity": null
  },
  {
    "line": 314,
    "token": 220,
    "index": 5,
    "confidence": 0.0,
    "severity": null
  },
  {
    "line": 314,
    "token": 220,
    "index": 6,
    "confidence": 0.0,
    "severity": null
  },
  {
    "line": 314,
    "token": 1441,
    "index": 7,
    "confidence": 0.0,
    "severity": null
  },
  {
    "line": 314,
    "token": 4406,
    "index": 8,
    "confidence": 0.0,
    "severity": null
  },
  {
    "line": 317,
    "token": 4299,
    "index": 0,
    "confidence": 0.0,
    "severity": null
  },
  {
    "line": 317,
    "token": 736,
    "index": 1,
    "confidence": 0.0,
    "severity": null
  },
  {
    "line": 317,
    "token": 9288,
    "index": 2,
    "confidence": 0.0,
    "severity": null
  },
  {
    "line": 317,
    "token": 7,
    "index": 3,
    "confidence": 0.0,
    "severity": null
  },
  {
    "line": 317,
    "token": 1891,
    "index": 4,
    "confidence": 0.0,
    "severity": null
  },
  {
    "line": 317,
    "token": 9288,
    "index": 5,
    "confidence": 0.0,
    "severity": null
  },
  {
    "line": 317,
    "token": 62,
    "index": 6,
    "confidence": 0.0,
    "severity": null
  },
  {
    "line": 317,
    "token": 11250,
    "index": 7,
    "confidence": 0.0,
    "severity": null
  },
  {
    "line": 317,
    "token": 25,
    "index": 8,
    "confidence": 0.0,
    "severity": null
  },
  {
    "line": 317,
    "token": 8633,
    "index": 9,
    "confidence": 0.0,
    "severity": null
  },
  {
    "line": 317,
    "token": 11,
    "index": 10,
    "confidence": 0.0,
    "severity": null
  },
  {
    "line": 317,
    "token": 351,
    "index": 11,
    "confidence": 0.0,
    "severity": null
  },
  {
    "line": 317,
    "token": 62,
    "index": 12,
    "confidence": 0.0,
    "severity": null
  },
  {
    "line": 317,
    "token": 14323,
    "index": 13,
    "confidence": 0.0,
    "severity": null
  },
  {
    "line": 317,
    "token": 8927,
    "index": 14,
    "confidence": 0.0,
    "severity": null
  },
  {
    "line": 317,
    "token": 25,
    "index": 15,
    "confidence": 0.0,
    "severity": null
  },
  {
    "line": 317,
    "token": 20512,
    "index": 16,
    "confidence": 0.0,
    "severity": null
  },
  {
    "line": 317,
    "token": 796,
    "index": 17,
    "confidence": 0.0,
    "severity": null
  },
  {
    "line": 317,
    "token": 10352,
    "index": 18,
    "confidence": 0.0,
    "severity": null
  },
  {
    "line": 317,
    "token": 8,
    "index": 19,
    "confidence": 0.0,
    "severity": null
  },
  {
    "line": 317,
    "token": 4613,
    "index": 20,
    "confidence": 0.0,
    "severity": null
  },
  {
    "line": 317,
    "token": 279,
    "index": 21,
    "confidence": 0.0,
    "severity": null
  },
  {
    "line": 317,
    "token": 67,
    "index": 22,
    "confidence": 0.0,
    "severity": null
  },
  {
    "line": 317,
    "token": 13,
    "index": 23,
    "confidence": 0.0,
    "severity": null
  },
  {
    "line": 317,
    "token": 6601,
    "index": 24,
    "confidence": 0.0,
    "severity": null
  },
  {
    "line": 317,
    "token": 19778,
    "index": 25,
    "confidence": 0.0,
    "severity": null
  },
  {
    "line": 317,
    "token": 25,
    "index": 26,
    "confidence": 0.0,
    "severity": null
  },
  {
    "line": 318,
    "token": 220,
    "index": 0,
    "confidence": 0.0,
    "severity": null
  },
  {
    "line": 318,
    "token": 220,
    "index": 1,
    "confidence": 0.0,
    "severity": null
  },
  {
    "line": 318,
    "token": 220,
    "index": 2,
    "confidence": 0.0,
    "severity": null
  },
  {
    "line": 318,
    "token": 1502,
    "index": 3,
    "confidence": 0.0,
    "severity": null
  },
  {
    "line": 318,
    "token": 62,
    "index": 4,
    "confidence": 0.0,
    "severity": null
  },
  {
    "line": 318,
    "token": 7568,
    "index": 5,
    "confidence": 0.0,
    "severity": null
  },
  {
    "line": 318,
    "token": 796,
    "index": 6,
    "confidence": 0.0,
    "severity": null
  },
  {
    "line": 318,
    "token": 1100,
    "index": 7,
    "confidence": 0.0,
    "severity": null
  },
  {
    "line": 318,
    "token": 62,
    "index": 8,
    "confidence": 0.0,
    "severity": null
  },
  {
    "line": 318,
    "token": 2875,
    "index": 9,
    "confidence": 0.0,
    "severity": null
  },
  {
    "line": 318,
    "token": 62,
    "index": 10,
    "confidence": 0.0,
    "severity": null
  },
  {
    "line": 318,
    "token": 7753,
    "index": 11,
    "confidence": 0.0,
    "severity": null
  },
  {
    "line": 318,
    "token": 7,
    "index": 12,
    "confidence": 0.0,
    "severity": null
  },
  {
    "line": 318,
    "token": 1891,
    "index": 13,
    "confidence": 0.0,
    "severity": null
  },
  {
    "line": 318,
    "token": 9288,
    "index": 14,
    "confidence": 0.0,
    "severity": null
  },
  {
    "line": 318,
    "token": 62,
    "index": 15,
    "confidence": 0.0,
    "severity": null
  },
  {
    "line": 318,
    "token": 11250,
    "index": 16,
    "confidence": 0.0,
    "severity": null
  },
  {
    "line": 318,
    "token": 14692,
    "index": 17,
    "confidence": 0.0,
    "severity": null
  },
  {
    "line": 318,
    "token": 2875,
    "index": 18,
    "confidence": 0.0,
    "severity": null
  },
  {
    "line": 318,
    "token": 62,
    "index": 19,
    "confidence": 0.0,
    "severity": null
  },
  {
    "line": 318,
    "token": 7753,
    "index": 20,
    "confidence": 0.0,
    "severity": null
  },
  {
    "line": 318,
    "token": 8973,
    "index": 21,
    "confidence": 0.0,
    "severity": null
  },
  {
    "line": 318,
    "token": 8,
    "index": 22,
    "confidence": 0.0,
    "severity": null
  }
]